{"single":[{"y":2012,"rows":[{"p":"2012HABI02","v":17,"r":1}]},{"y":2013,"rows":[{"p":"2012HABI02","v":17,"r":1}]},{"y":2014,"rows":[{"p":"2012HABI02","v":17,"r":1}]},{"y":2015,"rows":[{"p":"2012HABI02","v":17,"r":1}]},{"y":2016,"rows":[{"p":"2012HABI02","v":17,"r":1}]},{"y":2017,"rows":[{"p":"2012HABI02","v":17,"r":1}]},{"y":2018,"rows":[{"p":"2012HABI02","v":17,"r":1}]},{"y":2019,"rows":[{"p":"2012HABI02","v":17,"r":1}]},{"y":2020,"rows":[{"p":"2012HABI02","v":17,"r":1}]},{"y":2021,"rows":[{"p":"2012HABI02","v":17,"r":1}]},{"y":2022,"rows":[{"p":"2022SIRJ01","v":17,"r":1},{"p":"2022POON01","v":22,"r":2},{"p":"2022RICH24","v":23,"r":3},{"p":"2012HABI02","v":24,"r":4}]},{"y":2023,"rows":[{"p":"2022SIRJ01","v":19,"r":1},{"p":"2023HINK02","v":27,"r":2},{"p":"2022RICH24","v":28,"r":3},{"p":"2023YEKE01","v":32,"r":4},{"p":"2022POON01","v":35,"r":5},{"p":"2023DAVI27","v":35,"r":5},{"p":"2012HABI02","v":36,"r":7}]},{"y":2024,"rows":[{"p":"2022SIRJ01","v":18,"r":1},{"p":"2023HINK02","v":31,"r":2},{"p":"2022RICH24","v":41,"r":3},{"p":"2023YEKE01","v":47,"r":4},{"p":"2024PETE01","v":47,"r":4},{"p":"2022POON01","v":53,"r":6},{"p":"2023DAVI27","v":53,"r":6},{"p":"2024ACKI01","v":53,"r":6},{"p":"2024INKI01","v":53,"r":6},{"p":"2012HABI02","v":56,"r":10}]},{"y":2025,"rows":[{"p":"2022SIRJ01","v":24,"r":1},{"p":"2023HINK02","v":32,"r":2},{"p":"2025WILS03","v":39,"r":3},{"p":"2022RICH24","v":54,"r":4},{"p":"2024INKI01","v":60,"r":5},{"p":"2025SUTH01","v":61,"r":6},{"p":"2024PETE01","v":62,"r":7},{"p":"2023YEKE01","v":64,"r":8},{"p":"2024ACKI01","v":68,"r":9},{"p":"2023DAVI27","v":70,"r":10},{"p":"2022POON01","v":73,"r":11},{"p":"2012HABI02","v":75,"r":12},{"p":"2025ACKI01","v":75,"r":12},{"p":"2025WILS02","v":78,"r":14}]},{"y":2026,"rows":[{"p":"2022SIRJ01","v":24,"r":1},{"p":"2023HINK02","v":35,"r":2},{"p":"2025WILS03","v":41,"r":3},{"p":"2026RAMP06","v":63,"r":4},{"p":"2026SALA14","v":73,"r":5},{"p":"2022RICH24","v":84,"r":6},{"p":"2026GANP01","v":89,"r":7},{"p":"2025SUTH01","v":91,"r":8},{"p":"2026FULC01","v":107,"r":9},{"p":"2026MUHA03","v":110,"r":10},{"p":"2026BLAD02","v":111,"r":11},{"p":"2024INKI01","v":112,"r":12},{"p":"2026ROOP02","v":115,"r":13},{"p":"2026SAIS01","v":115,"r":13},{"p":"2024PETE01","v":116,"r":15}]}],"average":[{"y":2012,"rows":[{"p":"2012HABI02","v":16,"r":1}]},{"y":2013,"rows":[{"p":"2012HABI02","v":16,"r":1}]},{"y":2014,"rows":[{"p":"2012HABI02","v":16,"r":1}]},{"y":2015,"rows":[{"p":"2012HABI02","v":16,"r":1}]},{"y":2016,"rows":[{"p":"2012HABI02","v":16,"r":1}]},{"y":2017,"rows":[{"p":"2012HABI02","v":16,"r":1}]},{"y":2018,"rows":[{"p":"2012HABI02","v":16,"r":1}]},{"y":2019,"rows":[{"p":"2012HABI02","v":16,"r":1}]},{"y":2020,"rows":[{"p":"2012HABI02","v":16,"r":1}]},{"y":2021,"rows":[{"p":"2012HABI02","v":16,"r":1}]},{"y":2022,"rows":[{"p":"2022SIRJ01","v":16,"r":1},{"p":"2022POON01","v":19,"r":2},{"p":"2022RICH24","v":20,"r":3},{"p":"2012HABI02","v":21,"r":4}]},{"y":2023,"rows":[{"p":"2022SIRJ01","v":18,"r":1},{"p":"2023HINK02","v":22,"r":2},{"p":"2022RICH24","v":24,"r":3},{"p":"2023YEKE01","v":27,"r":4},{"p":"2022POON01","v":29,"r":5},{"p":"2012HABI02","v":30,"r":6},{"p":"2023DAVI27","v":30,"r":6}]},{"y":2024,"rows":[{"p":"2022SIRJ01","v":16,"r":1},{"p":"2023HINK02","v":26,"r":2},{"p":"2022RICH24","v":31,"r":3},{"p":"2024PETE01","v":38,"r":4},{"p":"2023YEKE01","v":39,"r":5},{"p":"2024ACKI01","v":40,"r":6},{"p":"2022POON01","v":42,"r":7},{"p":"2023DAVI27","v":43,"r":8},{"p":"2024INKI01","v":43,"r":8},{"p":"2012HABI02","v":46,"r":10}]},{"y":2025,"rows":[{"p":"2022SIRJ01","v":22,"r":1},{"p":"2023HINK02","v":27,"r":2},{"p":"2025WILS03","v":34,"r":3},{"p":"2022RICH24","v":44,"r":4},{"p":"2025SUTH01","v":51,"r":5},{"p":"2024INKI01","v":53,"r":6},{"p":"2024PETE01","v":54,"r":7},{"p":"2024ACKI01","v":56,"r":8},{"p":"2023YEKE01","v":57,"r":9},{"p":"2023DAVI27","v":60,"r":10},{"p":"2022POON01","v":62,"r":11},{"p":"2025ACKI01","v":64,"r":12},{"p":"2012HABI02","v":65,"r":13},{"p":"2025WILS02","v":67,"r":14}]},{"y":2026,"rows":[{"p":"2022SIRJ01","v":24,"r":1},{"p":"2023HINK02","v":28,"r":2},{"p":"2025WILS03","v":34,"r":3},{"p":"2026RAMP06","v":56,"r":4},{"p":"2026SALA14","v":61,"r":5},{"p":"2022RICH24","v":68,"r":6},{"p":"2026GANP01","v":77,"r":7},{"p":"2025SUTH01","v":84,"r":8},{"p":"2026FULC01","v":86,"r":9},{"p":"2026BLAD02","v":90,"r":10},{"p":"2026MUHA03","v":90,"r":10},{"p":"2024INKI01","v":95,"r":12},{"p":"2026RAMJ01","v":96,"r":13},{"p":"2026DEON01","v":99,"r":14},{"p":"2026SAIS01","v":103,"r":15}]}]}