{"single":[{"d":"2011-07-29","p":"2010YOUA01","v":6603,"c":"BarcelonaSummerOpen2011"},{"d":"2016-11-26","p":"2015SOBE02","v":2594,"c":"PSKubing2016"},{"d":"2017-10-13","p":"2017PORA02","v":7824,"c":"SpanishChampionship2017"},{"d":"2017-11-04","p":"2014LIBM01","v":9668,"c":"LatvianOpen2017"},{"d":"2017-12-16","p":"2016BARO04","v":1716,"c":"ItalianChampionship2017"},{"d":"2017-12-16","p":"2014YOSE01","v":5580,"c":"ItalianChampionship2017"},{"d":"2018-02-23","p":"2015YAKH01","v":1937,"c":"DneprNeverFails2018"},{"d":"2018-04-02","p":"2016SHAR16","v":3842,"c":"Israelspecial2018"},{"d":"2018-04-02","p":"2016BARO04","v":1665,"c":"Israelspecial2018"},{"d":"2018-04-02","p":"2017MAGE02","v":6189,"c":"Israelspecial2018"},{"d":"2018-04-02","p":"2015SOBE02","v":2359,"c":"Israelspecial2018"},{"d":"2018-04-02","p":"2017GABA02","v":3170,"c":"Israelspecial2018"},{"d":"2018-04-02","p":"2011FADL02","v":2175,"c":"Israelspecial2018"},{"d":"2018-04-02","p":"2014LIBM01","v":4384,"c":"Israelspecial2018"},{"d":"2018-04-02","p":"2017KACH04","v":3445,"c":"Israelspecial2018"},{"d":"2018-04-02","p":"2016STRA05","v":6763,"c":"Israelspecial2018"},{"d":"2018-04-02","p":"2017PORA02","v":5685,"c":"Israelspecial2018"},{"d":"2018-04-02","p":"2017REFA01","v":3471,"c":"Israelspecial2018"},{"d":"2018-06-23","p":"2014FADI01","v":4496,"c":"StJohnsSpring2018"},{"d":"2018-07-08","p":"2018SCHI01","v":4607,"c":"Brooklyn2018"},{"d":"2018-07-19","p":"2016BARO04","v":1193,"c":"Euro2018"},{"d":"2019-05-11","p":"2019TARA03","v":6999,"c":"BayAreaSpeedcubin162019"},{"d":"2019-06-08","p":"2014TAMI01","v":1835,"c":"SwissNationals2019"},{"d":"2019-08-23","p":"2014FADI01","v":3959,"c":"VancouverBigCubesOpen2019"},{"d":"2021-09-26","p":"2014FADI01","v":3786,"c":"BCCubingComebackB2021"},{"d":"2022-03-16","p":"2017TURM01","v":1469,"c":"KubiatEsther2022"},{"d":"2022-03-16","p":"2022VISH01","v":1382,"c":"KubiatEsther2022"},{"d":"2022-03-16","p":"2014TAMI01","v":1319,"c":"KubiatEsther2022"},{"d":"2022-03-16","p":"2015EGOZ01","v":1342,"c":"KubiatEsther2022"},{"d":"2022-03-16","p":"2019ANON21","v":1645,"c":"KubiatEsther2022"},{"d":"2022-03-16","p":"2022POUR02","v":1700,"c":"KubiatEsther2022"},{"d":"2022-03-16","p":"2019DORO03","v":2214,"c":"KubiatEsther2022"},{"d":"2022-03-16","p":"2019BENG02","v":2144,"c":"KubiatEsther2022"},{"d":"2022-03-16","p":"2016AMIT01","v":2542,"c":"KubiatEsther2022"},{"d":"2022-03-16","p":"2022YANI01","v":3392,"c":"KubiatEsther2022"},{"d":"2022-03-16","p":"2022HITT01","v":3042,"c":"KubiatEsther2022"},{"d":"2022-03-16","p":"2018SCHI01","v":2756,"c":"KubiatEsther2022"},{"d":"2022-03-16","p":"2022TURM01","v":2537,"c":"KubiatEsther2022"},{"d":"2022-03-16","p":"2014YOSE01","v":4049,"c":"KubiatEsther2022"},{"d":"2022-03-19","p":"2019TARA03","v":1909,"c":"CalPolySLOSpring2022"},{"d":"2022-03-27","p":"2019TARA03","v":1439,"c":"SacCubingXI2022"},{"d":"2022-07-14","p":"2016BARO04","v":887,"c":"Euro2022"},{"d":"2022-07-14","p":"2019ANON21","v":1633,"c":"Euro2022"},{"d":"2022-08-16","p":"2017TURM01","v":1172,"c":"IsraelChampionship2022"},{"d":"2022-08-16","p":"2019ANON21","v":1270,"c":"IsraelChampionship2022"},{"d":"2022-08-16","p":"2022VISH01","v":1381,"c":"IsraelChampionship2022"},{"d":"2022-08-16","p":"2022POUR02","v":1538,"c":"IsraelChampionship2022"},{"d":"2022-08-16","p":"2022YANI01","v":1779,"c":"IsraelChampionship2022"},{"d":"2022-08-16","p":"2022HOTE01","v":1749,"c":"IsraelChampionship2022"},{"d":"2022-08-16","p":"2019ENGE02","v":2209,"c":"IsraelChampionship2022"},{"d":"2022-08-16","p":"2022HITT01","v":2809,"c":"IsraelChampionship2022"},{"d":"2022-08-16","p":"2022MATY01","v":1811,"c":"IsraelChampionship2022"},{"d":"2022-08-16","p":"2022KAHA01","v":2601,"c":"IsraelChampionship2022"},{"d":"2022-08-16","p":"2022ALTA02","v":3212,"c":"IsraelChampionship2022"},{"d":"2022-08-16","p":"2022FEIN02","v":4095,"c":"IsraelChampionship2022"},{"d":"2022-08-16","p":"2018KRAS07","v":4546,"c":"IsraelChampionship2022"},{"d":"2022-08-16","p":"2016STRA05","v":5916,"c":"IsraelChampionship2022"},{"d":"2022-08-16","p":"2022ZIVA01","v":8620,"c":"IsraelChampionship2022"},{"d":"2022-12-21","p":"2022FREI09","v":2466,"c":"NRHanukkahSq1andSkewb2022"},{"d":"2022-12-21","p":"2022VISH01","v":1084,"c":"NRHanukkahSq1andSkewb2022"},{"d":"2022-12-21","p":"2019ANON21","v":1136,"c":"NRHanukkahSq1andSkewb2022"},{"d":"2022-12-21","p":"2022HITT01","v":1607,"c":"NRHanukkahSq1andSkewb2022"},{"d":"2022-12-21","p":"2022POUR02","v":855,"c":"NRHanukkahSq1andSkewb2022"},{"d":"2022-12-21","p":"2022RONY01","v":1149,"c":"NRHanukkahSq1andSkewb2022"},{"d":"2022-12-21","p":"2022HOTE01","v":1276,"c":"NRHanukkahSq1andSkewb2022"},{"d":"2022-12-21","p":"2022FEIN02","v":1430,"c":"NRHanukkahSq1andSkewb2022"},{"d":"2022-12-21","p":"2022SEGA01","v":1659,"c":"NRHanukkahSq1andSkewb2022"},{"d":"2022-12-21","p":"2022ZARI01","v":1899,"c":"NRHanukkahSq1andSkewb2022"},{"d":"2022-12-21","p":"2017TURM01","v":869,"c":"NRHanukkahSq1andSkewb2022"},{"d":"2022-12-21","p":"2022ALTA02","v":1554,"c":"NRHanukkahSq1andSkewb2022"},{"d":"2023-03-18","p":"2022YAMP01","v":2319,"c":"KorzennaSpringOpen2023"},{"d":"2023-04-01","p":"2023RUTE01","v":2960,"c":"BayAreaSpeedcubin432023"},{"d":"2023-05-06","p":"2022YAMP01","v":1295,"c":"Cube4funinJaroslaw2023"},{"d":"2023-05-09","p":"2018KRAS07","v":1381,"c":"MikesCubes2023"},{"d":"2023-05-09","p":"2022ZARI01","v":1252,"c":"MikesCubes2023"},{"d":"2023-05-09","p":"2022RONY01","v":845,"c":"MikesCubes2023"},{"d":"2023-05-09","p":"2022ALTA02","v":1403,"c":"MikesCubes2023"},{"d":"2023-05-09","p":"2019BENG02","v":857,"c":"MikesCubes2023"},{"d":"2023-05-09","p":"2022VISH01","v":1058,"c":"MikesCubes2023"},{"d":"2023-05-09","p":"2022KAHA01","v":771,"c":"MikesCubes2023"},{"d":"2023-05-09","p":"2022MATY01","v":1745,"c":"MikesCubes2023"},{"d":"2023-05-09","p":"2022ZIVA01","v":1394,"c":"MikesCubes2023"},{"d":"2023-05-09","p":"2023ORLO01","v":1895,"c":"MikesCubes2023"},{"d":"2023-06-04","p":"2023RUTE01","v":1621,"c":"BASC47BerkeleyPride2023"},{"d":"2023-06-17","p":"2019ANON21","v":1001,"c":"VegasSpeedcubingSummer2023"},{"d":"2023-07-01","p":"2022RONY01","v":805,"c":"SuffolkSummer2023"},{"d":"2023-07-08","p":"2016BARO04","v":840,"c":"KollaSummerCup2023"},{"d":"2023-07-08","p":"2014TAMI01","v":904,"c":"KollaSummerCup2023"},{"d":"2023-07-17","p":"2022RONY01","v":769,"c":"IsraelChampionship2023"},{"d":"2023-07-17","p":"2016AMIT01","v":1756,"c":"IsraelChampionship2023"},{"d":"2023-07-17","p":"2017TURM01","v":810,"c":"IsraelChampionship2023"},{"d":"2023-07-17","p":"2022HOTE01","v":846,"c":"IsraelChampionship2023"},{"d":"2023-07-17","p":"2022FREI09","v":1343,"c":"IsraelChampionship2023"},{"d":"2023-07-17","p":"2018KRAS07","v":1318,"c":"IsraelChampionship2023"},{"d":"2023-07-17","p":"2022MATY01","v":1574,"c":"IsraelChampionship2023"},{"d":"2023-07-17","p":"2019DORO03","v":2026,"c":"IsraelChampionship2023"},{"d":"2023-07-17","p":"2019BENG02","v":846,"c":"IsraelChampionship2023"},{"d":"2023-07-17","p":"2023ORLO01","v":1532,"c":"IsraelChampionship2023"},{"d":"2023-07-17","p":"2022VISH01","v":988,"c":"IsraelChampionship2023"},{"d":"2023-07-17","p":"2022KAHA01","v":710,"c":"IsraelChampionship2023"},{"d":"2023-07-29","p":"2022KHAN53","v":6625,"c":"TallinnOpen2023"},{"d":"2023-08-12","p":"2022KAHA01","v":708,"c":"WC2023"},{"d":"2023-09-23","p":"2022YAMP01","v":698,"c":"Cube4funWislaMasters2023"},{"d":"2023-11-18","p":"2023RUTE01","v":1173,"c":"BerkeleyFall2023"},{"d":"2024-01-14","p":"2023RUTE01","v":1027,"c":"BayAreaSpeedcubin55SanRamon2024"},{"d":"2024-02-16","p":"2022ZARI01","v":710,"c":"WeekendCubingAIsrael2024"},{"d":"2024-02-16","p":"2022POUR02","v":708,"c":"WeekendCubingAIsrael2024"},{"d":"2024-02-16","p":"2023ORLO01","v":1120,"c":"WeekendCubingAIsrael2024"},{"d":"2024-02-16","p":"2022FREI09","v":936,"c":"WeekendCubingAIsrael2024"},{"d":"2024-02-16","p":"2022ATSM01","v":1081,"c":"WeekendCubingAIsrael2024"},{"d":"2024-02-16","p":"2022HITT01","v":1047,"c":"WeekendCubingAIsrael2024"},{"d":"2024-02-16","p":"2023SAND02","v":1823,"c":"WeekendCubingAIsrael2024"},{"d":"2024-02-17","p":"2015EGOZ01","v":1260,"c":"WeekendCubingCIsrael2024"},{"d":"2024-05-03","p":"2016BARO04","v":756,"c":"CSMIsrael2024"},{"d":"2024-05-03","p":"2022FREI09","v":812,"c":"CSMIsrael2024"},{"d":"2024-05-03","p":"2017TURM01","v":677,"c":"CSMIsrael2024"},{"d":"2024-05-03","p":"2019BENG02","v":827,"c":"CSMIsrael2024"},{"d":"2024-05-03","p":"2022MATY01","v":994,"c":"CSMIsrael2024"},{"d":"2024-05-03","p":"2018KRAS07","v":1000,"c":"CSMIsrael2024"},{"d":"2024-05-03","p":"2022ZIVA01","v":1071,"c":"CSMIsrael2024"},{"d":"2024-05-03","p":"2016AMIT01","v":876,"c":"CSMIsrael2024"},{"d":"2024-05-03","p":"2019TARA03","v":1428,"c":"CSMIsrael2024"},{"d":"2024-05-03","p":"2019ANON21","v":908,"c":"CSMIsrael2024"},{"d":"2024-05-03","p":"2023SAND02","v":1462,"c":"CSMIsrael2024"},{"d":"2024-05-03","p":"2019DORO03","v":1653,"c":"CSMIsrael2024"},{"d":"2024-05-03","p":"2022KHAN53","v":1708,"c":"CSMIsrael2024"},{"d":"2024-05-26","p":"2022MATY01","v":926,"c":"MikesCubes2024"},{"d":"2024-05-26","p":"2018KRAS07","v":977,"c":"MikesCubes2024"},{"d":"2024-05-26","p":"2023SAND02","v":1460,"c":"MikesCubes2024"},{"d":"2024-07-25","p":"2022VISH01","v":973,"c":"Euro2024"},{"d":"2024-07-25","p":"2022KHAN53","v":1635,"c":"Euro2024"},{"d":"2024-08-18","p":"2016BARO04","v":686,"c":"IsraelChampionship2024"},{"d":"2024-08-18","p":"2019BENG02","v":691,"c":"IsraelChampionship2024"},{"d":"2024-08-18","p":"2018KRAS07","v":878,"c":"IsraelChampionship2024"},{"d":"2024-08-18","p":"2019TARA03","v":1146,"c":"IsraelChampionship2024"},{"d":"2024-08-18","p":"2023ORLO01","v":1051,"c":"IsraelChampionship2024"},{"d":"2024-08-18","p":"2016SHAR16","v":3838,"c":"IsraelChampionship2024"},{"d":"2024-08-23","p":"2022KHAN53","v":1467,"c":"KarkiOpen2024"},{"d":"2024-09-05","p":"2022ZARI01","v":665,"c":"AroundtheClockIsrael2024"},{"d":"2024-09-05","p":"2022POUR02","v":705,"c":"AroundtheClockIsrael2024"},{"d":"2024-09-05","p":"2022ATSM01","v":803,"c":"AroundtheClockIsrael2024"},{"d":"2024-09-05","p":"2023SAND02","v":1327,"c":"AroundtheClockIsrael2024"},{"d":"2024-10-12","p":"2023ORLO01","v":874,"c":"CyprusNationals2024"},{"d":"2024-11-01","p":"2022KAHA01","v":636,"c":"RubiksUKChampionship2024"},{"d":"2024-11-22","p":"2022ZARI01","v":526,"c":"TheParityMenaceIsrael2024"},{"d":"2024-11-22","p":"2022POUR02","v":669,"c":"TheParityMenaceIsrael2024"},{"d":"2024-11-22","p":"2016AMIT01","v":657,"c":"TheParityMenaceIsrael2024"},{"d":"2024-11-22","p":"2023SAND02","v":1058,"c":"TheParityMenaceIsrael2024"},{"d":"2024-11-22","p":"2022VISH01","v":897,"c":"TheParityMenaceIsrael2024"},{"d":"2024-11-22","p":"2022KHAN53","v":1177,"c":"TheParityMenaceIsrael2024"},{"d":"2025-04-15","p":"2022FEIN02","v":1292,"c":"HaifaCubing2025"},{"d":"2025-04-15","p":"2022KHAN53","v":1127,"c":"HaifaCubing2025"},{"d":"2025-04-15","p":"2023SAND02","v":947,"c":"HaifaCubing2025"},{"d":"2025-04-15","p":"2022MATY01","v":924,"c":"HaifaCubing2025"},{"d":"2025-04-15","p":"2022POUR02","v":668,"c":"HaifaCubing2025"},{"d":"2025-04-15","p":"2023ORLO01","v":791,"c":"HaifaCubing2025"},{"d":"2025-05-02","p":"2022SEGA01","v":1526,"c":"ReturnoftheCubersIsrael2025"},{"d":"2025-05-02","p":"2022KHAN53","v":896,"c":"ReturnoftheCubersIsrael2025"},{"d":"2025-05-02","p":"2022ZARI01","v":490,"c":"ReturnoftheCubersIsrael2025"},{"d":"2025-05-02","p":"2023SAND02","v":909,"c":"ReturnoftheCubersIsrael2025"},{"d":"2025-08-25","p":"2019TARA03","v":1076,"c":"IsraelChampionship2025"},{"d":"2025-08-25","p":"2022SEGA01","v":1364,"c":"IsraelChampionship2025"},{"d":"2025-08-25","p":"2023SAND02","v":861,"c":"IsraelChampionship2025"},{"d":"2025-08-25","p":"2022RONY01","v":677,"c":"IsraelChampionship2025"},{"d":"2025-10-24","p":"2022SEGA01","v":1298,"c":"RogueSquanIsrael2025"},{"d":"2025-10-24","p":"2022FREI09","v":748,"c":"RogueSquanIsrael2025"},{"d":"2025-10-24","p":"2022POUR02","v":621,"c":"RogueSquanIsrael2025"},{"d":"2025-12-17","p":"2022HOTE01","v":836,"c":"NRHanukkahBIsrael2025"},{"d":"2025-12-17","p":"2022ZARI01","v":481,"c":"NRHanukkahBIsrael2025"},{"d":"2025-12-17","p":"2022ATSM01","v":670,"c":"NRHanukkahBIsrael2025"},{"d":"2025-12-17","p":"2022RONY01","v":662,"c":"NRHanukkahBIsrael2025"},{"d":"2025-12-27","p":"2016BARO04","v":563,"c":"CyprusNationals2025"},{"d":"2026-01-01","p":"2022RONY01","v":629,"c":"NewYearIsrael2026"},{"d":"2026-07-16","p":"2022MATY01","v":825,"c":"Euro2026"}],"single_r":[{"d":"2011-07-29","p":"2010YOUA01","v":6603,"c":"BarcelonaSummerOpen2011"},{"d":"2016-11-26","p":"2015SOBE02","v":2594,"c":"PSKubing2016"},{"d":"2016-11-26","p":"2015SOBE02","v":3331,"c":"PSKubing2016"},{"d":"2017-10-13","p":"2017PORA02","v":7824,"c":"SpanishChampionship2017"},{"d":"2017-11-04","p":"2014LIBM01","v":9668,"c":"LatvianOpen2017"},{"d":"2017-12-16","p":"2016BARO04","v":1716,"c":"ItalianChampionship2017"},{"d":"2017-12-16","p":"2016BARO04","v":1729,"c":"ItalianChampionship2017"},{"d":"2017-12-16","p":"2014YOSE01","v":5580,"c":"ItalianChampionship2017"},{"d":"2018-02-23","p":"2015YAKH01","v":1937,"c":"DneprNeverFails2018"},{"d":"2018-02-23","p":"2015YAKH01","v":2409,"c":"DneprNeverFails2018"},{"d":"2018-03-24","p":"2015YAKH01","v":3692,"c":"LSD2018"},{"d":"2018-04-02","p":"2016BARO04","v":1665,"c":"Israelspecial2018"},{"d":"2018-04-02","p":"2016BARO04","v":1729,"c":"Israelspecial2018"},{"d":"2018-04-02","p":"2011FADL02","v":2175,"c":"Israelspecial2018"},{"d":"2018-04-02","p":"2011FADL02","v":2195,"c":"Israelspecial2018"},{"d":"2018-04-02","p":"2015SOBE02","v":2359,"c":"Israelspecial2018"},{"d":"2018-04-02","p":"2015SOBE02","v":2570,"c":"Israelspecial2018"},{"d":"2018-04-02","p":"2017GABA02","v":3170,"c":"Israelspecial2018"},{"d":"2018-04-02","p":"2017GABA02","v":3430,"c":"Israelspecial2018"},{"d":"2018-04-02","p":"2017KACH04","v":3445,"c":"Israelspecial2018"},{"d":"2018-06-01","p":"2015YAKH01","v":2224,"c":"UkrainianOpen2018"},{"d":"2018-07-07","p":"2015YAKH01","v":2130,"c":"WhiteCityCubing2018"},{"d":"2018-07-19","p":"2016BARO04","v":1193,"c":"Euro2018"},{"d":"2018-07-19","p":"2016BARO04","v":1721,"c":"Euro2018"},{"d":"2018-08-11","p":"2015YAKH01","v":2570,"c":"KharkivOpen2018"},{"d":"2018-11-09","p":"2015YAKH01","v":2410,"c":"SmartCubeFest2018"},{"d":"2018-11-09","p":"2015YAKH01","v":2483,"c":"SmartCubeFest2018"},{"d":"2019-03-15","p":"2016BARO04","v":1236,"c":"DenmarkFriends2019"},{"d":"2019-06-08","p":"2016BARO04","v":1214,"c":"SwissNationals2019"},{"d":"2019-06-08","p":"2014TAMI01","v":1835,"c":"SwissNationals2019"},{"d":"2019-06-08","p":"2016BARO04","v":2010,"c":"SwissNationals2019"},{"d":"2021-11-26","p":"2016BARO04","v":1194,"c":"CubingUSAWesternChampionship2021"},{"d":"2022-03-16","p":"2016BARO04","v":1223,"c":"KubiatEsther2022"},{"d":"2022-03-16","p":"2014TAMI01","v":1319,"c":"KubiatEsther2022"},{"d":"2022-03-16","p":"2015EGOZ01","v":1342,"c":"KubiatEsther2022"},{"d":"2022-03-16","p":"2022VISH01","v":1382,"c":"KubiatEsther2022"},{"d":"2022-03-16","p":"2017TURM01","v":1469,"c":"KubiatEsther2022"},{"d":"2022-03-16","p":"2019ANON21","v":1645,"c":"KubiatEsther2022"},{"d":"2022-03-16","p":"2022POUR02","v":1700,"c":"KubiatEsther2022"},{"d":"2022-03-27","p":"2019TARA03","v":1439,"c":"SacCubingXI2022"},{"d":"2022-07-14","p":"2016BARO04","v":887,"c":"Euro2022"},{"d":"2022-07-14","p":"2016BARO04","v":913,"c":"Euro2022"},{"d":"2022-07-14","p":"2015EGOZ01","v":1357,"c":"Euro2022"},{"d":"2022-07-14","p":"2015EGOZ01","v":1505,"c":"Euro2022"},{"d":"2022-07-14","p":"2019ANON21","v":1633,"c":"Euro2022"},{"d":"2022-08-16","p":"2016BARO04","v":1168,"c":"IsraelChampionship2022"},{"d":"2022-08-16","p":"2017TURM01","v":1172,"c":"IsraelChampionship2022"},{"d":"2022-08-16","p":"2019ANON21","v":1270,"c":"IsraelChampionship2022"},{"d":"2022-08-16","p":"2014TAMI01","v":1351,"c":"IsraelChampionship2022"},{"d":"2022-08-16","p":"2022VISH01","v":1381,"c":"IsraelChampionship2022"},{"d":"2022-10-07","p":"2014TAMI01","v":1370,"c":"SpanishChampionship2022"},{"d":"2022-12-21","p":"2022POUR02","v":855,"c":"NRHanukkahSq1andSkewb2022"},{"d":"2022-12-21","p":"2017TURM01","v":869,"c":"NRHanukkahSq1andSkewb2022"},{"d":"2022-12-21","p":"2022POUR02","v":923,"c":"NRHanukkahSq1andSkewb2022"},{"d":"2022-12-21","p":"2022POUR02","v":953,"c":"NRHanukkahSq1andSkewb2022"},{"d":"2022-12-21","p":"2017TURM01","v":1075,"c":"NRHanukkahSq1andSkewb2022"},{"d":"2022-12-21","p":"2022VISH01","v":1084,"c":"NRHanukkahSq1andSkewb2022"},{"d":"2022-12-21","p":"2022VISH01","v":1103,"c":"NRHanukkahSq1andSkewb2022"},{"d":"2022-12-21","p":"2022VISH01","v":1109,"c":"NRHanukkahSq1andSkewb2022"},{"d":"2022-12-21","p":"2019ANON21","v":1136,"c":"NRHanukkahSq1andSkewb2022"},{"d":"2022-12-21","p":"2022RONY01","v":1149,"c":"NRHanukkahSq1andSkewb2022"},{"d":"2023-05-09","p":"2022KAHA01","v":771,"c":"MikesCubes2023"},{"d":"2023-05-09","p":"2022RONY01","v":845,"c":"MikesCubes2023"},{"d":"2023-05-09","p":"2019BENG02","v":857,"c":"MikesCubes2023"},{"d":"2023-05-09","p":"2022POUR02","v":899,"c":"MikesCubes2023"},{"d":"2023-05-09","p":"2022KAHA01","v":931,"c":"MikesCubes2023"},{"d":"2023-05-09","p":"2016BARO04","v":988,"c":"MikesCubes2023"},{"d":"2023-05-09","p":"2022VISH01","v":1058,"c":"MikesCubes2023"},{"d":"2023-05-09","p":"2022POUR02","v":1074,"c":"MikesCubes2023"},{"d":"2023-06-17","p":"2019ANON21","v":1001,"c":"VegasSpeedcubingSummer2023"},{"d":"2023-07-01","p":"2022RONY01","v":805,"c":"SuffolkSummer2023"},{"d":"2023-07-01","p":"2022RONY01","v":829,"c":"SuffolkSummer2023"},{"d":"2023-07-08","p":"2016BARO04","v":840,"c":"KollaSummerCup2023"},{"d":"2023-07-08","p":"2014TAMI01","v":904,"c":"KollaSummerCup2023"},{"d":"2023-07-17","p":"2022KAHA01","v":710,"c":"IsraelChampionship2023"},{"d":"2023-07-17","p":"2022RONY01","v":769,"c":"IsraelChampionship2023"},{"d":"2023-07-17","p":"2022KAHA01","v":780,"c":"IsraelChampionship2023"},{"d":"2023-07-17","p":"2022RONY01","v":803,"c":"IsraelChampionship2023"},{"d":"2023-07-17","p":"2017TURM01","v":810,"c":"IsraelChampionship2023"},{"d":"2023-07-17","p":"2022RONY01","v":816,"c":"IsraelChampionship2023"},{"d":"2023-07-17","p":"2022HOTE01","v":846,"c":"IsraelChampionship2023"},{"d":"2023-07-17","p":"2019BENG02","v":846,"c":"IsraelChampionship2023"},{"d":"2023-07-17","p":"2016BARO04","v":849,"c":"IsraelChampionship2023"},{"d":"2023-08-12","p":"2022KAHA01","v":708,"c":"WC2023"},{"d":"2023-09-23","p":"2022YAMP01","v":698,"c":"Cube4funWislaMasters2023"},{"d":"2024-02-16","p":"2022POUR02","v":708,"c":"WeekendCubingAIsrael2024"},{"d":"2024-02-16","p":"2022ZARI01","v":710,"c":"WeekendCubingAIsrael2024"},{"d":"2024-02-16","p":"2022KAHA01","v":746,"c":"WeekendCubingAIsrael2024"},{"d":"2024-02-16","p":"2022KAHA01","v":759,"c":"WeekendCubingAIsrael2024"},{"d":"2024-02-16","p":"2022POUR02","v":788,"c":"WeekendCubingAIsrael2024"},{"d":"2024-05-03","p":"2017TURM01","v":677,"c":"CSMIsrael2024"},{"d":"2024-05-03","p":"2016BARO04","v":756,"c":"CSMIsrael2024"},{"d":"2024-05-03","p":"2022POUR02","v":764,"c":"CSMIsrael2024"},{"d":"2024-05-03","p":"2022POUR02","v":772,"c":"CSMIsrael2024"},{"d":"2024-05-03","p":"2022POUR02","v":780,"c":"CSMIsrael2024"},{"d":"2024-05-26","p":"2022POUR02","v":710,"c":"MikesCubes2024"},{"d":"2024-05-26","p":"2017TURM01","v":716,"c":"MikesCubes2024"},{"d":"2024-05-26","p":"2022ZARI01","v":763,"c":"MikesCubes2024"},{"d":"2024-05-26","p":"2022ZARI01","v":767,"c":"MikesCubes2024"},{"d":"2024-08-18","p":"2016BARO04","v":686,"c":"IsraelChampionship2024"},{"d":"2024-08-18","p":"2019BENG02","v":691,"c":"IsraelChampionship2024"},{"d":"2024-08-18","p":"2022KAHA01","v":738,"c":"IsraelChampionship2024"},{"d":"2024-08-18","p":"2016BARO04","v":739,"c":"IsraelChampionship2024"},{"d":"2024-09-05","p":"2022ZARI01","v":665,"c":"AroundtheClockIsrael2024"},{"d":"2024-09-05","p":"2022POUR02","v":705,"c":"AroundtheClockIsrael2024"},{"d":"2024-11-01","p":"2022KAHA01","v":636,"c":"RubiksUKChampionship2024"},{"d":"2024-11-01","p":"2022KAHA01","v":670,"c":"RubiksUKChampionship2024"},{"d":"2024-11-22","p":"2022ZARI01","v":526,"c":"TheParityMenaceIsrael2024"},{"d":"2024-11-22","p":"2016AMIT01","v":657,"c":"TheParityMenaceIsrael2024"},{"d":"2024-11-22","p":"2022POUR02","v":669,"c":"TheParityMenaceIsrael2024"},{"d":"2024-11-22","p":"2022POUR02","v":670,"c":"TheParityMenaceIsrael2024"},{"d":"2024-11-22","p":"2022ZARI01","v":694,"c":"TheParityMenaceIsrael2024"},{"d":"2025-04-15","p":"2022ZARI01","v":539,"c":"HaifaCubing2025"},{"d":"2025-04-15","p":"2022ZARI01","v":668,"c":"HaifaCubing2025"},{"d":"2025-04-15","p":"2022POUR02","v":668,"c":"HaifaCubing2025"},{"d":"2025-05-02","p":"2022ZARI01","v":490,"c":"ReturnoftheCubersIsrael2025"},{"d":"2025-05-02","p":"2022ZARI01","v":502,"c":"ReturnoftheCubersIsrael2025"},{"d":"2025-07-03","p":"2022ZARI01","v":588,"c":"WC2025"},{"d":"2025-07-03","p":"2022ZARI01","v":640,"c":"WC2025"},{"d":"2025-08-25","p":"2022ZARI01","v":606,"c":"IsraelChampionship2025"},{"d":"2025-08-25","p":"2022ZARI01","v":640,"c":"IsraelChampionship2025"},{"d":"2025-10-24","p":"2022ZARI01","v":572,"c":"RogueSquanIsrael2025"},{"d":"2025-10-24","p":"2022POUR02","v":621,"c":"RogueSquanIsrael2025"},{"d":"2025-12-17","p":"2022ZARI01","v":481,"c":"NRHanukkahBIsrael2025"},{"d":"2025-12-17","p":"2022ZARI01","v":650,"c":"NRHanukkahBIsrael2025"},{"d":"2025-12-17","p":"2022RONY01","v":662,"c":"NRHanukkahBIsrael2025"},{"d":"2025-12-27","p":"2016BARO04","v":563,"c":"CyprusNationals2025"},{"d":"2026-01-01","p":"2022RONY01","v":629,"c":"NewYearIsrael2026"},{"d":"2026-07-02","p":"2022ZARI01","v":502,"c":"SlovakChampionship2026"},{"d":"2026-07-16","p":"2022ZARI01","v":596,"c":"Euro2026"}],"average":[{"d":"2016-11-26","p":"2015SOBE02","v":3430,"c":"PSKubing2016"},{"d":"2017-12-16","p":"2016BARO04","v":1931,"c":"ItalianChampionship2017"},{"d":"2018-02-23","p":"2015YAKH01","v":2817,"c":"DneprNeverFails2018"},{"d":"2018-04-02","p":"2016SHAR16","v":4673,"c":"Israelspecial2018"},{"d":"2018-04-02","p":"2017MAGE02","v":9177,"c":"Israelspecial2018"},{"d":"2018-04-02","p":"2017GABA02","v":4225,"c":"Israelspecial2018"},{"d":"2018-04-02","p":"2011FADL02","v":3267,"c":"Israelspecial2018"},{"d":"2018-04-02","p":"2014LIBM01","v":5833,"c":"Israelspecial2018"},{"d":"2018-04-02","p":"2017KACH04","v":3597,"c":"Israelspecial2018"},{"d":"2018-04-02","p":"2016STRA05","v":9339,"c":"Israelspecial2018"},{"d":"2018-04-02","p":"2017PORA02","v":7165,"c":"Israelspecial2018"},{"d":"2018-04-02","p":"2017REFA01","v":5047,"c":"Israelspecial2018"},{"d":"2018-07-19","p":"2016BARO04","v":1798,"c":"Euro2018"},{"d":"2019-06-08","p":"2014TAMI01","v":3067,"c":"SwissNationals2019"},{"d":"2019-08-23","p":"2014FADI01","v":5336,"c":"VancouverBigCubesOpen2019"},{"d":"2021-09-26","p":"2014FADI01","v":4938,"c":"BCCubingComebackB2021"},{"d":"2021-11-26","p":"2016BARO04","v":1648,"c":"CubingUSAWesternChampionship2021"},{"d":"2022-03-16","p":"2016BARO04","v":1471,"c":"KubiatEsther2022"},{"d":"2022-03-16","p":"2017TURM01","v":1638,"c":"KubiatEsther2022"},{"d":"2022-03-16","p":"2022VISH01","v":1663,"c":"KubiatEsther2022"},{"d":"2022-03-16","p":"2014TAMI01","v":1681,"c":"KubiatEsther2022"},{"d":"2022-03-16","p":"2015EGOZ01","v":1742,"c":"KubiatEsther2022"},{"d":"2022-03-16","p":"2019ANON21","v":1970,"c":"KubiatEsther2022"},{"d":"2022-03-16","p":"2022POUR02","v":2343,"c":"KubiatEsther2022"},{"d":"2022-03-16","p":"2019DORO03","v":2963,"c":"KubiatEsther2022"},{"d":"2022-03-16","p":"2019BENG02","v":3037,"c":"KubiatEsther2022"},{"d":"2022-03-16","p":"2016AMIT01","v":3094,"c":"KubiatEsther2022"},{"d":"2022-03-16","p":"2022BORE01","v":3732,"c":"KubiatEsther2022"},{"d":"2022-03-16","p":"2022YANI01","v":3734,"c":"KubiatEsther2022"},{"d":"2022-03-16","p":"2022HITT01","v":3870,"c":"KubiatEsther2022"},{"d":"2022-03-16","p":"2017EVEN01","v":4341,"c":"KubiatEsther2022"},{"d":"2022-03-19","p":"2019TARA03","v":2525,"c":"CalPolySLOSpring2022"},{"d":"2022-03-27","p":"2019TARA03","v":1806,"c":"SacCubingXI2022"},{"d":"2022-07-14","p":"2015EGOZ01","v":1688,"c":"Euro2022"},{"d":"2022-08-16","p":"2016BARO04","v":1445,"c":"IsraelChampionship2022"},{"d":"2022-08-16","p":"2017TURM01","v":1470,"c":"IsraelChampionship2022"},{"d":"2022-08-16","p":"2019ANON21","v":1510,"c":"IsraelChampionship2022"},{"d":"2022-08-16","p":"2022VISH01","v":1597,"c":"IsraelChampionship2022"},{"d":"2022-08-16","p":"2022POUR02","v":1888,"c":"IsraelChampionship2022"},{"d":"2022-08-16","p":"2022YANI01","v":2330,"c":"IsraelChampionship2022"},{"d":"2022-08-16","p":"2022HOTE01","v":2573,"c":"IsraelChampionship2022"},{"d":"2022-08-16","p":"2019ENGE02","v":2687,"c":"IsraelChampionship2022"},{"d":"2022-08-16","p":"2017EVEN01","v":3051,"c":"IsraelChampionship2022"},{"d":"2022-08-16","p":"2022HITT01","v":3146,"c":"IsraelChampionship2022"},{"d":"2022-08-16","p":"2022MATY01","v":3252,"c":"IsraelChampionship2022"},{"d":"2022-08-16","p":"2022KAHA01","v":3677,"c":"IsraelChampionship2022"},{"d":"2022-08-16","p":"2022ALTA02","v":3924,"c":"IsraelChampionship2022"},{"d":"2022-12-21","p":"2022FREI09","v":4060,"c":"NRHanukkahSq1andSkewb2022"},{"d":"2022-12-21","p":"2022VISH01","v":1366,"c":"NRHanukkahSq1andSkewb2022"},{"d":"2022-12-21","p":"2019ANON21","v":1397,"c":"NRHanukkahSq1andSkewb2022"},{"d":"2022-12-21","p":"2022HITT01","v":2018,"c":"NRHanukkahSq1andSkewb2022"},{"d":"2022-12-21","p":"2022POUR02","v":1098,"c":"NRHanukkahSq1andSkewb2022"},{"d":"2022-12-21","p":"2022RONY01","v":1518,"c":"NRHanukkahSq1andSkewb2022"},{"d":"2022-12-21","p":"2022HOTE01","v":1625,"c":"NRHanukkahSq1andSkewb2022"},{"d":"2022-12-21","p":"2022FEIN02","v":1767,"c":"NRHanukkahSq1andSkewb2022"},{"d":"2022-12-21","p":"2022SEGA01","v":2023,"c":"NRHanukkahSq1andSkewb2022"},{"d":"2022-12-21","p":"2022ZARI01","v":2168,"c":"NRHanukkahSq1andSkewb2022"},{"d":"2022-12-21","p":"2017TURM01","v":1318,"c":"NRHanukkahSq1andSkewb2022"},{"d":"2022-12-21","p":"2022ALTA02","v":2327,"c":"NRHanukkahSq1andSkewb2022"},{"d":"2023-03-18","p":"2022YAMP01","v":3150,"c":"KorzennaSpringOpen2023"},{"d":"2023-04-01","p":"2023RUTE01","v":3652,"c":"BayAreaSpeedcubin432023"},{"d":"2023-05-06","p":"2022YAMP01","v":1662,"c":"Cube4funinJaroslaw2023"},{"d":"2023-05-09","p":"2018KRAS07","v":1595,"c":"MikesCubes2023"},{"d":"2023-05-09","p":"2022ZARI01","v":1670,"c":"MikesCubes2023"},{"d":"2023-05-09","p":"2022POUR02","v":910,"c":"MikesCubes2023"},{"d":"2023-05-09","p":"2016BARO04","v":1198,"c":"MikesCubes2023"},{"d":"2023-05-09","p":"2022RONY01","v":1051,"c":"MikesCubes2023"},{"d":"2023-05-09","p":"2022ALTA02","v":1888,"c":"MikesCubes2023"},{"d":"2023-05-09","p":"2019BENG02","v":1054,"c":"MikesCubes2023"},{"d":"2023-05-09","p":"2022VISH01","v":1344,"c":"MikesCubes2023"},{"d":"2023-05-09","p":"2022KAHA01","v":1026,"c":"MikesCubes2023"},{"d":"2023-05-09","p":"2022MATY01","v":2361,"c":"MikesCubes2023"},{"d":"2023-05-09","p":"2022ZIVA01","v":1655,"c":"MikesCubes2023"},{"d":"2023-05-09","p":"2023ORLO01","v":2475,"c":"MikesCubes2023"},{"d":"2023-06-04","p":"2023RUTE01","v":2304,"c":"BASC47BerkeleyPride2023"},{"d":"2023-06-30","p":"2023RUTE01","v":2233,"c":"CubingUSAWesternChampionship2023"},{"d":"2023-07-01","p":"2022RONY01","v":988,"c":"SuffolkSummer2023"},{"d":"2023-07-08","p":"2016BARO04","v":1011,"c":"KollaSummerCup2023"},{"d":"2023-07-08","p":"2014TAMI01","v":1510,"c":"KollaSummerCup2023"},{"d":"2023-07-17","p":"2016AMIT01","v":1959,"c":"IsraelChampionship2023"},{"d":"2023-07-17","p":"2017TURM01","v":1063,"c":"IsraelChampionship2023"},{"d":"2023-07-17","p":"2022BORE01","v":3250,"c":"IsraelChampionship2023"},{"d":"2023-07-17","p":"2022HOTE01","v":1299,"c":"IsraelChampionship2023"},{"d":"2023-07-17","p":"2022FREI09","v":2001,"c":"IsraelChampionship2023"},{"d":"2023-07-17","p":"2022ZIVA01","v":1625,"c":"IsraelChampionship2023"},{"d":"2023-07-17","p":"2022MATY01","v":1778,"c":"IsraelChampionship2023"},{"d":"2023-07-17","p":"2019DORO03","v":2420,"c":"IsraelChampionship2023"},{"d":"2023-07-17","p":"2016BARO04","v":1001,"c":"IsraelChampionship2023"},{"d":"2023-07-17","p":"2023ORLO01","v":2021,"c":"IsraelChampionship2023"},{"d":"2023-07-17","p":"2014TAMI01","v":1494,"c":"IsraelChampionship2023"},{"d":"2023-07-17","p":"2022VISH01","v":1341,"c":"IsraelChampionship2023"},{"d":"2023-07-17","p":"2022KAHA01","v":997,"c":"IsraelChampionship2023"},{"d":"2023-08-12","p":"2022KAHA01","v":892,"c":"WC2023"},{"d":"2023-09-23","p":"2022YAMP01","v":1184,"c":"Cube4funWislaMasters2023"},{"d":"2023-11-18","p":"2023RUTE01","v":1531,"c":"BerkeleyFall2023"},{"d":"2024-02-16","p":"2022KAHA01","v":856,"c":"WeekendCubingAIsrael2024"},{"d":"2024-02-16","p":"2022ZARI01","v":990,"c":"WeekendCubingAIsrael2024"},{"d":"2024-02-16","p":"2022POUR02","v":822,"c":"WeekendCubingAIsrael2024"},{"d":"2024-02-16","p":"2023ORLO01","v":1343,"c":"WeekendCubingAIsrael2024"},{"d":"2024-02-16","p":"2022FREI09","v":1556,"c":"WeekendCubingAIsrael2024"},{"d":"2024-02-16","p":"2022ATSM01","v":1672,"c":"WeekendCubingAIsrael2024"},{"d":"2024-02-16","p":"2022HITT01","v":1676,"c":"WeekendCubingAIsrael2024"},{"d":"2024-02-16","p":"2023SAND02","v":2444,"c":"WeekendCubingAIsrael2024"},{"d":"2024-02-17","p":"2022HOTE01","v":1031,"c":"WeekendCubingCIsrael2024"},{"d":"2024-02-17","p":"2015EGOZ01","v":1583,"c":"WeekendCubingCIsrael2024"},{"d":"2024-05-03","p":"2016BARO04","v":898,"c":"CSMIsrael2024"},{"d":"2024-05-03","p":"2022FREI09","v":1013,"c":"CSMIsrael2024"},{"d":"2024-05-03","p":"2017TURM01","v":1061,"c":"CSMIsrael2024"},{"d":"2024-05-03","p":"2014TAMI01","v":1309,"c":"CSMIsrael2024"},{"d":"2024-05-03","p":"2022ATSM01","v":1435,"c":"CSMIsrael2024"},{"d":"2024-05-03","p":"2022MATY01","v":1328,"c":"CSMIsrael2024"},{"d":"2024-05-03","p":"2018KRAS07","v":1480,"c":"CSMIsrael2024"},{"d":"2024-05-03","p":"2022ZIVA01","v":1571,"c":"CSMIsrael2024"},{"d":"2024-05-03","p":"2016AMIT01","v":1119,"c":"CSMIsrael2024"},{"d":"2024-05-03","p":"2019TARA03","v":1568,"c":"CSMIsrael2024"},{"d":"2024-05-03","p":"2019ANON21","v":1257,"c":"CSMIsrael2024"},{"d":"2024-05-03","p":"2023SAND02","v":1941,"c":"CSMIsrael2024"},{"d":"2024-05-03","p":"2019DORO03","v":2015,"c":"CSMIsrael2024"},{"d":"2024-05-26","p":"2022ZARI01","v":919,"c":"MikesCubes2024"},{"d":"2024-05-26","p":"2017TURM01","v":904,"c":"MikesCubes2024"},{"d":"2024-05-26","p":"2022VISH01","v":1301,"c":"MikesCubes2024"},{"d":"2024-05-26","p":"2022ZIVA01","v":1501,"c":"MikesCubes2024"},{"d":"2024-05-26","p":"2014TAMI01","v":1306,"c":"MikesCubes2024"},{"d":"2024-05-26","p":"2023SAND02","v":1794,"c":"MikesCubes2024"},{"d":"2024-07-25","p":"2016BARO04","v":891,"c":"Euro2024"},{"d":"2024-07-25","p":"2022VISH01","v":1125,"c":"Euro2024"},{"d":"2024-07-25","p":"2022MATY01","v":1323,"c":"Euro2024"},{"d":"2024-08-18","p":"2022KAHA01","v":850,"c":"IsraelChampionship2024"},{"d":"2024-08-18","p":"2019BENG02","v":1031,"c":"IsraelChampionship2024"},{"d":"2024-08-18","p":"2017TURM01","v":880,"c":"IsraelChampionship2024"},{"d":"2024-08-18","p":"2022MATY01","v":1212,"c":"IsraelChampionship2024"},{"d":"2024-08-18","p":"2018KRAS07","v":1252,"c":"IsraelChampionship2024"},{"d":"2024-08-18","p":"2019TARA03","v":1512,"c":"IsraelChampionship2024"},{"d":"2024-09-05","p":"2022ZARI01","v":821,"c":"AroundtheClockIsrael2024"},{"d":"2024-09-05","p":"2022ATSM01","v":1308,"c":"AroundtheClockIsrael2024"},{"d":"2024-09-05","p":"2023SAND02","v":1537,"c":"AroundtheClockIsrael2024"},{"d":"2024-09-08","p":"2023RUTE01","v":1517,"c":"BASC64LIVESSF2024"},{"d":"2024-10-12","p":"2023ORLO01","v":1108,"c":"CyprusNationals2024"},{"d":"2024-11-01","p":"2022KAHA01","v":768,"c":"RubiksUKChampionship2024"},{"d":"2024-11-22","p":"2016BARO04","v":873,"c":"TheParityMenaceIsrael2024"},{"d":"2024-11-22","p":"2023SAND02","v":1253,"c":"TheParityMenaceIsrael2024"},{"d":"2024-11-22","p":"2022ATSM01","v":1080,"c":"TheParityMenaceIsrael2024"},{"d":"2024-11-22","p":"2014TAMI01","v":1233,"c":"TheParityMenaceIsrael2024"},{"d":"2024-11-22","p":"2018KRAS07","v":1122,"c":"TheParityMenaceIsrael2024"},{"d":"2025-04-15","p":"2023SAND02","v":1192,"c":"HaifaCubing2025"},{"d":"2025-04-15","p":"2022MATY01","v":1133,"c":"HaifaCubing2025"},{"d":"2025-05-02","p":"2022ZARI01","v":621,"c":"ReturnoftheCubersIsrael2025"},{"d":"2025-05-02","p":"2023SAND02","v":1086,"c":"ReturnoftheCubersIsrael2025"},{"d":"2025-07-03","p":"2023RUTE01","v":1458,"c":"WC2025"},{"d":"2025-08-25","p":"2019TARA03","v":1444,"c":"IsraelChampionship2025"},{"d":"2025-08-25","p":"2022SEGA01","v":1694,"c":"IsraelChampionship2025"},{"d":"2025-08-25","p":"2022ZIVA01","v":1500,"c":"IsraelChampionship2025"},{"d":"2025-08-25","p":"2014TAMI01","v":1194,"c":"IsraelChampionship2025"},{"d":"2025-08-25","p":"2022MATY01","v":1044,"c":"IsraelChampionship2025"},{"d":"2025-08-25","p":"2022ATSM01","v":955,"c":"IsraelChampionship2025"},{"d":"2025-08-25","p":"2022FREI09","v":962,"c":"IsraelChampionship2025"},{"d":"2025-08-25","p":"2024KEDA01","v":2423,"c":"IsraelChampionship2025"},{"d":"2025-08-25","p":"2022RONY01","v":933,"c":"IsraelChampionship2025"},{"d":"2025-10-24","p":"2022ATSM01","v":940,"c":"RogueSquanIsrael2025"},{"d":"2025-10-24","p":"2022FREI09","v":868,"c":"RogueSquanIsrael2025"},{"d":"2025-10-24","p":"2024KEDA01","v":1862,"c":"RogueSquanIsrael2025"},{"d":"2025-10-24","p":"2022POUR02","v":787,"c":"RogueSquanIsrael2025"},{"d":"2025-12-17","p":"2022RONY01","v":851,"c":"NRHanukkahBIsrael2025"},{"d":"2026-01-01","p":"2024KEDA01","v":1709,"c":"NewYearIsrael2026"},{"d":"2026-07-02","p":"2024KEDA01","v":1084,"c":"SlovakChampionship2026"},{"d":"2026-07-02","p":"2022ATSM01","v":881,"c":"SlovakChampionship2026"}],"average_r":[{"d":"2016-11-26","p":"2015SOBE02","v":3430,"c":"PSKubing2016"},{"d":"2016-11-26","p":"2015SOBE02","v":3614,"c":"PSKubing2016"},{"d":"2017-12-16","p":"2016BARO04","v":1931,"c":"ItalianChampionship2017"},{"d":"2017-12-16","p":"2016BARO04","v":2883,"c":"ItalianChampionship2017"},{"d":"2018-02-23","p":"2015YAKH01","v":2817,"c":"DneprNeverFails2018"},{"d":"2018-02-23","p":"2015YAKH01","v":3614,"c":"DneprNeverFails2018"},{"d":"2018-03-24","p":"2015YAKH01","v":3956,"c":"LSD2018"},{"d":"2018-04-02","p":"2016BARO04","v":1950,"c":"Israelspecial2018"},{"d":"2018-04-02","p":"2016BARO04","v":1959,"c":"Israelspecial2018"},{"d":"2018-04-02","p":"2011FADL02","v":3267,"c":"Israelspecial2018"},{"d":"2018-04-02","p":"2015SOBE02","v":3445,"c":"Israelspecial2018"},{"d":"2018-04-02","p":"2015SOBE02","v":3460,"c":"Israelspecial2018"},{"d":"2018-04-02","p":"2011FADL02","v":3464,"c":"Israelspecial2018"},{"d":"2018-04-02","p":"2017KACH04","v":3597,"c":"Israelspecial2018"},{"d":"2018-04-02","p":"2017GABA02","v":4225,"c":"Israelspecial2018"},{"d":"2018-06-01","p":"2015YAKH01","v":3037,"c":"UkrainianOpen2018"},{"d":"2018-07-07","p":"2015YAKH01","v":3119,"c":"WhiteCityCubing2018"},{"d":"2018-07-19","p":"2016BARO04","v":1798,"c":"Euro2018"},{"d":"2018-07-19","p":"2016BARO04","v":2116,"c":"Euro2018"},{"d":"2018-08-11","p":"2015YAKH01","v":3319,"c":"KharkivOpen2018"},{"d":"2018-10-12","p":"2015YAKH01","v":3293,"c":"UkrainianNationals2018"},{"d":"2018-11-09","p":"2015YAKH01","v":3041,"c":"SmartCubeFest2018"},{"d":"2019-03-15","p":"2016BARO04","v":2069,"c":"DenmarkFriends2019"},{"d":"2019-06-08","p":"2016BARO04","v":2184,"c":"SwissNationals2019"},{"d":"2019-06-08","p":"2016BARO04","v":2502,"c":"SwissNationals2019"},{"d":"2019-06-08","p":"2014TAMI01","v":3067,"c":"SwissNationals2019"},{"d":"2021-11-26","p":"2016BARO04","v":1648,"c":"CubingUSAWesternChampionship2021"},{"d":"2022-03-16","p":"2016BARO04","v":1471,"c":"KubiatEsther2022"},{"d":"2022-03-16","p":"2017TURM01","v":1638,"c":"KubiatEsther2022"},{"d":"2022-03-16","p":"2022VISH01","v":1663,"c":"KubiatEsther2022"},{"d":"2022-03-16","p":"2014TAMI01","v":1681,"c":"KubiatEsther2022"},{"d":"2022-03-16","p":"2015EGOZ01","v":1742,"c":"KubiatEsther2022"},{"d":"2022-03-16","p":"2019ANON21","v":1970,"c":"KubiatEsther2022"},{"d":"2022-03-16","p":"2022POUR02","v":2343,"c":"KubiatEsther2022"},{"d":"2022-03-27","p":"2019TARA03","v":1806,"c":"SacCubingXI2022"},{"d":"2022-07-14","p":"2016BARO04","v":1506,"c":"Euro2022"},{"d":"2022-07-14","p":"2016BARO04","v":1517,"c":"Euro2022"},{"d":"2022-07-14","p":"2015EGOZ01","v":1688,"c":"Euro2022"},{"d":"2022-07-14","p":"2015EGOZ01","v":1940,"c":"Euro2022"},{"d":"2022-08-16","p":"2016BARO04","v":1445,"c":"IsraelChampionship2022"},{"d":"2022-08-16","p":"2017TURM01","v":1470,"c":"IsraelChampionship2022"},{"d":"2022-08-16","p":"2019ANON21","v":1510,"c":"IsraelChampionship2022"},{"d":"2022-08-16","p":"2022VISH01","v":1597,"c":"IsraelChampionship2022"},{"d":"2022-12-21","p":"2022POUR02","v":1098,"c":"NRHanukkahSq1andSkewb2022"},{"d":"2022-12-21","p":"2022POUR02","v":1113,"c":"NRHanukkahSq1andSkewb2022"},{"d":"2022-12-21","p":"2022POUR02","v":1221,"c":"NRHanukkahSq1andSkewb2022"},{"d":"2022-12-21","p":"2017TURM01","v":1318,"c":"NRHanukkahSq1andSkewb2022"},{"d":"2022-12-21","p":"2022VISH01","v":1366,"c":"NRHanukkahSq1andSkewb2022"},{"d":"2022-12-21","p":"2019ANON21","v":1397,"c":"NRHanukkahSq1andSkewb2022"},{"d":"2022-12-21","p":"2022VISH01","v":1469,"c":"NRHanukkahSq1andSkewb2022"},{"d":"2022-12-21","p":"2019ANON21","v":1484,"c":"NRHanukkahSq1andSkewb2022"},{"d":"2022-12-21","p":"2022VISH01","v":1488,"c":"NRHanukkahSq1andSkewb2022"},{"d":"2023-05-09","p":"2022POUR02","v":910,"c":"MikesCubes2023"},{"d":"2023-05-09","p":"2022KAHA01","v":1026,"c":"MikesCubes2023"},{"d":"2023-05-09","p":"2022RONY01","v":1051,"c":"MikesCubes2023"},{"d":"2023-05-09","p":"2019BENG02","v":1054,"c":"MikesCubes2023"},{"d":"2023-05-09","p":"2022KAHA01","v":1091,"c":"MikesCubes2023"},{"d":"2023-05-09","p":"2016BARO04","v":1198,"c":"MikesCubes2023"},{"d":"2023-05-09","p":"2019BENG02","v":1261,"c":"MikesCubes2023"},{"d":"2023-05-09","p":"2022RONY01","v":1342,"c":"MikesCubes2023"},{"d":"2023-05-09","p":"2022VISH01","v":1344,"c":"MikesCubes2023"},{"d":"2023-07-01","p":"2022RONY01","v":988,"c":"SuffolkSummer2023"},{"d":"2023-07-01","p":"2022RONY01","v":1191,"c":"SuffolkSummer2023"},{"d":"2023-07-08","p":"2016BARO04","v":1011,"c":"KollaSummerCup2023"},{"d":"2023-07-17","p":"2022POUR02","v":961,"c":"IsraelChampionship2023"},{"d":"2023-07-17","p":"2022KAHA01","v":997,"c":"IsraelChampionship2023"},{"d":"2023-07-17","p":"2016BARO04","v":1001,"c":"IsraelChampionship2023"},{"d":"2023-07-17","p":"2022RONY01","v":1033,"c":"IsraelChampionship2023"},{"d":"2023-07-17","p":"2017TURM01","v":1063,"c":"IsraelChampionship2023"},{"d":"2023-07-17","p":"2019BENG02","v":1064,"c":"IsraelChampionship2023"},{"d":"2023-07-17","p":"2019BENG02","v":1074,"c":"IsraelChampionship2023"},{"d":"2023-07-17","p":"2016BARO04","v":1086,"c":"IsraelChampionship2023"},{"d":"2023-07-17","p":"2022RONY01","v":1088,"c":"IsraelChampionship2023"},{"d":"2023-08-12","p":"2022KAHA01","v":892,"c":"WC2023"},{"d":"2023-08-12","p":"2016BARO04","v":1076,"c":"WC2023"},{"d":"2024-02-16","p":"2022POUR02","v":822,"c":"WeekendCubingAIsrael2024"},{"d":"2024-02-16","p":"2022KAHA01","v":856,"c":"WeekendCubingAIsrael2024"},{"d":"2024-02-16","p":"2022KAHA01","v":987,"c":"WeekendCubingAIsrael2024"},{"d":"2024-02-16","p":"2022ZARI01","v":990,"c":"WeekendCubingAIsrael2024"},{"d":"2024-02-16","p":"2022ZARI01","v":1010,"c":"WeekendCubingAIsrael2024"},{"d":"2024-02-17","p":"2022HOTE01","v":1031,"c":"WeekendCubingCIsrael2024"},{"d":"2024-05-03","p":"2016BARO04","v":898,"c":"CSMIsrael2024"},{"d":"2024-05-03","p":"2022POUR02","v":915,"c":"CSMIsrael2024"},{"d":"2024-05-03","p":"2016BARO04","v":964,"c":"CSMIsrael2024"},{"d":"2024-05-03","p":"2022POUR02","v":994,"c":"CSMIsrael2024"},{"d":"2024-05-26","p":"2022POUR02","v":893,"c":"MikesCubes2024"},{"d":"2024-05-26","p":"2017TURM01","v":904,"c":"MikesCubes2024"},{"d":"2024-05-26","p":"2022ZARI01","v":919,"c":"MikesCubes2024"},{"d":"2024-05-26","p":"2016BARO04","v":924,"c":"MikesCubes2024"},{"d":"2024-07-25","p":"2016BARO04","v":891,"c":"Euro2024"},{"d":"2024-08-18","p":"2022KAHA01","v":850,"c":"IsraelChampionship2024"},{"d":"2024-08-18","p":"2017TURM01","v":880,"c":"IsraelChampionship2024"},{"d":"2024-08-18","p":"2022POUR02","v":883,"c":"IsraelChampionship2024"},{"d":"2024-08-18","p":"2016BARO04","v":909,"c":"IsraelChampionship2024"},{"d":"2024-08-18","p":"2022ZARI01","v":922,"c":"IsraelChampionship2024"},{"d":"2024-09-05","p":"2022ZARI01","v":821,"c":"AroundtheClockIsrael2024"},{"d":"2024-09-05","p":"2022POUR02","v":840,"c":"AroundtheClockIsrael2024"},{"d":"2024-11-01","p":"2022KAHA01","v":768,"c":"RubiksUKChampionship2024"},{"d":"2024-11-22","p":"2022ZARI01","v":868,"c":"TheParityMenaceIsrael2024"},{"d":"2024-11-22","p":"2016BARO04","v":873,"c":"TheParityMenaceIsrael2024"},{"d":"2025-04-15","p":"2022POUR02","v":847,"c":"HaifaCubing2025"},{"d":"2025-04-15","p":"2022ZARI01","v":877,"c":"HaifaCubing2025"},{"d":"2025-05-02","p":"2022ZARI01","v":621,"c":"ReturnoftheCubersIsrael2025"},{"d":"2025-05-02","p":"2022POUR02","v":877,"c":"ReturnoftheCubersIsrael2025"},{"d":"2025-05-02","p":"2022ZARI01","v":890,"c":"ReturnoftheCubersIsrael2025"},{"d":"2025-07-03","p":"2022ZARI01","v":748,"c":"WC2025"},{"d":"2025-07-03","p":"2022ZARI01","v":781,"c":"WC2025"},{"d":"2025-08-25","p":"2022ZARI01","v":744,"c":"IsraelChampionship2025"},{"d":"2025-08-25","p":"2022ZARI01","v":767,"c":"IsraelChampionship2025"},{"d":"2025-10-24","p":"2022ZARI01","v":730,"c":"RogueSquanIsrael2025"},{"d":"2025-10-24","p":"2022POUR02","v":787,"c":"RogueSquanIsrael2025"},{"d":"2025-10-24","p":"2022FREI09","v":868,"c":"RogueSquanIsrael2025"},{"d":"2025-12-17","p":"2022ZARI01","v":793,"c":"NRHanukkahBIsrael2025"},{"d":"2025-12-17","p":"2022ZARI01","v":797,"c":"NRHanukkahBIsrael2025"},{"d":"2026-01-01","p":"2022ZARI01","v":749,"c":"NewYearIsrael2026"},{"d":"2026-01-01","p":"2022ZARI01","v":815,"c":"NewYearIsrael2026"},{"d":"2026-07-02","p":"2022ZARI01","v":699,"c":"SlovakChampionship2026"},{"d":"2026-07-02","p":"2022ZARI01","v":822,"c":"SlovakChampionship2026"}],"persons":{"2010YOUA01":{"name":"Maor Youavian","country":"Israel","iso2":"IL"},"2015SOBE02":{"name":"Lia Sobel","country":"Israel","iso2":"IL"},"2017PORA02":{"name":"Yuval Porat","country":"Israel","iso2":"IL"},"2014LIBM01":{"name":"Ron Libman","country":"Israel","iso2":"IL"},"2016BARO04":{"name":"Ben Baron","country":"Israel","iso2":"IL"},"2014YOSE01":{"name":"Daniel Yosef","country":"Israel","iso2":"IL"},"2015YAKH01":{"name":"Daniel Yakhkind (Даніель Яхкінд)","country":"Ukraine","iso2":"UA"},"2016SHAR16":{"name":"Avshalom Sharavani","country":"Israel","iso2":"IL"},"2017MAGE02":{"name":"Carmel Magen","country":"Israel","iso2":"IL"},"2017GABA02":{"name":"Liran Gabay","country":"Israel","iso2":"IL"},"2011FADL02":{"name":"Noam Fadlon","country":"Israel","iso2":"IL"},"2017KACH04":{"name":"Shmulik Kachuriner","country":"Israel","iso2":"IL"},"2016STRA05":{"name":"Yoni Strassberg","country":"Israel","iso2":"IL"},"2017REFA01":{"name":"Ziv Refaeli","country":"Israel","iso2":"IL"},"2014FADI01":{"name":"Sagiv Fadida","country":"Israel","iso2":"IL"},"2018SCHI01":{"name":"Eitan Schild","country":"Israel","iso2":"IL"},"2019TARA03":{"name":"Guy Taragano","country":"Israel","iso2":"IL"},"2014TAMI01":{"name":"Roy Tamir","country":"Israel","iso2":"IL"},"2017TURM01":{"name":"Itamar Turm","country":"Israel","iso2":"IL"},"2022VISH01":{"name":"Yoav Vishne","country":"Israel","iso2":"IL"},"2015EGOZ01":{"name":"Ofek Egozi","country":"Israel","iso2":"IL"},"2019ANON21":{"name":"Anonymous","country":"Israel","iso2":"IL"},"2022POUR02":{"name":"Netanel Pour","country":"Israel","iso2":"IL"},"2019DORO03":{"name":"Niv Doron","country":"Israel","iso2":"IL"},"2019BENG02":{"name":"Liav Bengayev","country":"Israel","iso2":"IL"},"2016AMIT01":{"name":"Elai Amit-Wender","country":"Israel","iso2":"IL"},"2022YANI01":{"name":"Porat Yaniv","country":"Israel","iso2":"IL"},"2022HITT01":{"name":"Eviatar Hittin","country":"Israel","iso2":"IL"},"2022TURM01":{"name":"Binyamin Turm","country":"Israel","iso2":"IL"},"2022HOTE01":{"name":"Maor Hoter","country":"Israel","iso2":"IL"},"2019ENGE02":{"name":"Achia Engel","country":"Israel","iso2":"IL"},"2022MATY01":{"name":"Ben Matyas","country":"Israel","iso2":"IL"},"2022KAHA01":{"name":"Libi Wohlfeiler Kahaty","country":"Israel","iso2":"IL"},"2022ALTA02":{"name":"Yahav Tetro Altal","country":"Israel","iso2":"IL"},"2022FEIN02":{"name":"Eilam Fein","country":"Israel","iso2":"IL"},"2018KRAS07":{"name":"Levi Krassenstein","country":"Israel","iso2":"IL"},"2022ZIVA01":{"name":"Amitai Ziv","country":"Israel","iso2":"IL"},"2022FREI09":{"name":"Eyal Freifeld","country":"Israel","iso2":"IL"},"2022RONY01":{"name":"Yair Ron","country":"Israel","iso2":"IL"},"2022SEGA01":{"name":"Inbar Segal","country":"Israel","iso2":"IL"},"2022ZARI01":{"name":"Guy Zarian","country":"Israel","iso2":"IL"},"2022YAMP01":{"name":"Amit Yampolsky","country":"Israel","iso2":"IL"},"2023RUTE01":{"name":"Jonathan Rutenberg","country":"Israel","iso2":"IL"},"2023ORLO01":{"name":"Erez Orlovsky","country":"Israel","iso2":"IL"},"2022KHAN53":{"name":"Yoel Khanin","country":"Israel","iso2":"IL"},"2022ATSM01":{"name":"Yoav Atsmon","country":"Israel","iso2":"IL"},"2023SAND02":{"name":"Mark Sander","country":"Israel","iso2":"IL"},"2022BORE01":{"name":"Erez Borenshtein","country":"Israel","iso2":"IL"},"2017EVEN01":{"name":"Daniel Even","country":"Israel","iso2":"IL"},"2024KEDA01":{"name":"Omer Kedar","country":"Israel","iso2":"IL"}},"comps":{"BarcelonaSummerOpen2011":{"name":"Barcelona Open 2011"},"PSKubing2016":{"name":"PSKubing 2016"},"SpanishChampionship2017":{"name":"Spanish Championship 2017"},"LatvianOpen2017":{"name":"Latvian Open 2017"},"ItalianChampionship2017":{"name":"Italian Championship 2017"},"DneprNeverFails2018":{"name":"Dnepr Never Fails 2018"},"Israelspecial2018":{"name":"Israel Special 2018"},"StJohnsSpring2018":{"name":"St. John's Spring Open 2018"},"Brooklyn2018":{"name":"Brooklyn 2018"},"Euro2018":{"name":"WCA Euro 2018"},"BayAreaSpeedcubin162019":{"name":"Bay Area Speedcubin' 16 2019"},"SwissNationals2019":{"name":"Swiss Nationals 2019"},"VancouverBigCubesOpen2019":{"name":"Vancouver Big Cubes Open 2019"},"BCCubingComebackB2021":{"name":"BCCC B 2021"},"KubiatEsther2022":{"name":"Kubiat Esther 2022"},"CalPolySLOSpring2022":{"name":"Cal Poly SLO Spring 2022"},"SacCubingXI2022":{"name":"SacCubing XI 2022"},"Euro2022":{"name":"WCA European Championship 2022"},"IsraelChampionship2022":{"name":"Israel Championship 2022"},"NRHanukkahSq1andSkewb2022":{"name":"NR Hanukkah: Sq-1 & Skewb 2022"},"KorzennaSpringOpen2023":{"name":"Korzenna Spring Open 2023"},"BayAreaSpeedcubin432023":{"name":"Bay Area Speedcubin' 43 2023"},"Cube4funinJaroslaw2023":{"name":"Cube4fun in Jarosław 2023"},"MikesCubes2023":{"name":"Mike's Cubes 2023"},"BASC47BerkeleyPride2023":{"name":"BASC 47 - Berkeley Pride 2023"},"VegasSpeedcubingSummer2023":{"name":"Vegas Speedcubing Summer 2023"},"SuffolkSummer2023":{"name":"Suffolk Summer 2023"},"KollaSummerCup2023":{"name":"Kolla Summer Cup 2023"},"IsraelChampionship2023":{"name":"Israel Championship 2023"},"TallinnOpen2023":{"name":"Tallinn Open 2023"},"WC2023":{"name":"WCA World Championship 2023"},"Cube4funWislaMasters2023":{"name":"Cube4fun Wisła 2023"},"BerkeleyFall2023":{"name":"Berkeley Fall 2023"},"BayAreaSpeedcubin55SanRamon2024":{"name":"BASC 55 - San Ramon 2024"},"WeekendCubingAIsrael2024":{"name":"Weekend Cubing A Israel 2024"},"WeekendCubingCIsrael2024":{"name":"Weekend Cubing C Israel 2024"},"CSMIsrael2024":{"name":"C.S.M. Israel 2024"},"MikesCubes2024":{"name":"Mike's Cubes 2024"},"Euro2024":{"name":"WCA European Championship 2024"},"IsraelChampionship2024":{"name":"Israel Championship 2024"},"KarkiOpen2024":{"name":"Kārķi Open 2024"},"AroundtheClockIsrael2024":{"name":"Around the Clock Israel 2024"},"CyprusNationals2024":{"name":"Cyprus Nationals 2024"},"RubiksUKChampionship2024":{"name":"Rubik's UK Championship 2024"},"TheParityMenaceIsrael2024":{"name":"The Parity Menace Israel 2024"},"HaifaCubing2025":{"name":"Haifa Cubing 2025"},"ReturnoftheCubersIsrael2025":{"name":"Return of the Cubers Israel 2025"},"IsraelChampionship2025":{"name":"Israel Championship 2025"},"RogueSquanIsrael2025":{"name":"Rogue Squan Israel 2025"},"NRHanukkahBIsrael2025":{"name":"NR Hanukkah B Israel 2025"},"CyprusNationals2025":{"name":"Cyprus Nationals 2025"},"NewYearIsrael2026":{"name":"New Year Israel 2026"},"Euro2026":{"name":"WCA European Championship 2026"},"LSD2018":{"name":"Lviv Spring Days 2018"},"UkrainianOpen2018":{"name":"Ukrainian Open 2018"},"WhiteCityCubing2018":{"name":"White City Cubing 2018"},"KharkivOpen2018":{"name":"Kharkiv Open 2018"},"SmartCubeFest2018":{"name":"Smart Cube Fest 2018"},"DenmarkFriends2019":{"name":"Denmark & Friends 2019"},"CubingUSAWesternChampionship2021":{"name":"CubingUSA Western Champs 2021"},"SpanishChampionship2022":{"name":"Spanish Championship 2022"},"WC2025":{"name":"WCA World Championship 2025"},"SlovakChampionship2026":{"name":"Slovak Championship 2026"},"CubingUSAWesternChampionship2023":{"name":"Western Championship 2023"},"BASC64LIVESSF2024":{"name":"BASC 64 LIVE - SSF 2024"},"UkrainianNationals2018":{"name":"Ukrainian Nationals 2018"}}}