{"single":[{"d":"2011-12-16","p":"2010MOND01","v":76000,"c":"SpanishChampionship2011"},{"d":"2012-01-26","p":"2010MOND01","v":73900,"c":"BarcelonaWinterOpen2012"},{"d":"2013-01-05","p":"2011QUEZ01","v":44013,"c":"CampeonatoSudamericano2013"},{"d":"2013-01-05","p":"2011ARAN01","v":59374,"c":"CampeonatoSudamericano2013"},{"d":"2013-02-22","p":"2010MOND01","v":67800,"c":"UAMOpen2013"},{"d":"2013-03-16","p":"2011ARAN01","v":49204,"c":"ArequipaSummer2013"},{"d":"2013-04-05","p":"2011LUJA01","v":35769,"c":"NacionalPerubik2013"},{"d":"2013-04-05","p":"2011QUEZ01","v":43527,"c":"NacionalPerubik2013"},{"d":"2013-04-05","p":"2013VALD02","v":43980,"c":"NacionalPerubik2013"},{"d":"2013-07-20","p":"2013VALD02","v":31747,"c":"TrujilloOpen2013"},{"d":"2013-07-20","p":"2012ROBL01","v":36031,"c":"TrujilloOpen2013"},{"d":"2013-10-04","p":"2011ARAN01","v":38657,"c":"MarianoMelgar2013"},{"d":"2013-10-04","p":"2011CUBA02","v":45054,"c":"MarianoMelgar2013"},{"d":"2013-10-26","p":"2013CAST06","v":30173,"c":"PalacioDelCubo2013"},{"d":"2013-10-26","p":"2012ROBL01","v":29839,"c":"PalacioDelCubo2013"},{"d":"2013-10-26","p":"2011QUEZ01","v":36670,"c":"PalacioDelCubo2013"},{"d":"2013-10-26","p":"2011CUBA02","v":44798,"c":"PalacioDelCubo2013"},{"d":"2013-10-26","p":"2011CORA01","v":45747,"c":"PalacioDelCubo2013"},{"d":"2014-02-07","p":"2013VALD02","v":25836,"c":"CulturalOpen2014"},{"d":"2014-02-07","p":"2011CUBA02","v":44217,"c":"CulturalOpen2014"},{"d":"2014-03-08","p":"2013VALD02","v":23898,"c":"BackToThePalace2014"},{"d":"2014-03-08","p":"2013CAST06","v":25386,"c":"BackToThePalace2014"},{"d":"2014-03-08","p":"2011CUBA02","v":42409,"c":"BackToThePalace2014"},{"d":"2014-03-08","p":"2013VERA03","v":54559,"c":"BackToThePalace2014"},{"d":"2014-06-20","p":"2011CUBA02","v":39591,"c":"UniRubik2014"},{"d":"2014-07-12","p":"2011CUBA02","v":38690,"c":"MarianoMelgar2014"},{"d":"2014-07-12","p":"2013HUAN03","v":41486,"c":"MarianoMelgar2014"},{"d":"2014-09-06","p":"2013TEMP01","v":46282,"c":"TCGLima2014"},{"d":"2014-09-06","p":"2011QUEZ01","v":34425,"c":"TCGLima2014"},{"d":"2014-10-24","p":"2013VERA03","v":38561,"c":"IIOpenArguedas2014"},{"d":"2014-10-24","p":"2011CUBA02","v":36589,"c":"IIOpenArguedas2014"},{"d":"2014-11-29","p":"2013BERD02","v":40924,"c":"GameProTour2014"},{"d":"2015-01-31","p":"2013TEMP01","v":42252,"c":"NewAvgeOpen2015"},{"d":"2015-01-31","p":"2013HUAN30","v":32720,"c":"NewAvgeOpen2015"},{"d":"2015-01-31","p":"2015TELL01","v":23241,"c":"NewAvgeOpen2015"},{"d":"2015-06-13","p":"2013HUAN03","v":37905,"c":"HunterOpen2015"},{"d":"2015-06-13","p":"2011CUBA02","v":24837,"c":"HunterOpen2015"},{"d":"2015-06-13","p":"2015TELL01","v":20400,"c":"HunterOpen2015"},{"d":"2015-07-08","p":"2013HUAN03","v":34072,"c":"TCGAndFriendsAQP2015"},{"d":"2015-07-11","p":"2014GUTI04","v":31382,"c":"TCGAndFriends2015"},{"d":"2015-07-11","p":"2015ELIA03","v":40297,"c":"TCGAndFriends2015"},{"d":"2015-07-17","p":"2015TELL01","v":19159,"c":"WC2015"},{"d":"2016-01-23","p":"2015TELL01","v":18803,"c":"TorneoAventuraCubica2016"},{"d":"2016-01-23","p":"2014CORD04","v":29375,"c":"TorneoAventuraCubica2016"},{"d":"2016-01-23","p":"2013VERA03","v":34771,"c":"TorneoAventuraCubica2016"},{"d":"2016-01-23","p":"2013ANAM01","v":40007,"c":"TorneoAventuraCubica2016"},{"d":"2016-02-12","p":"2011CUBA02","v":20638,"c":"UchiMontevideo2016"},{"d":"2016-03-20","p":"2015TELL01","v":16920,"c":"CrazyCubesSummer2016"},{"d":"2016-03-20","p":"2013VALD02","v":23760,"c":"CrazyCubesSummer2016"},{"d":"2016-07-01","p":"2011CUBA02","v":20179,"c":"BoliviaNationals2016"},{"d":"2016-07-01","p":"2014ZARA01","v":48715,"c":"BoliviaNationals2016"},{"d":"2016-07-16","p":"2014RUIZ10","v":24649,"c":"NacionalPerubik2016"},{"d":"2016-07-16","p":"2014CORD04","v":26417,"c":"NacionalPerubik2016"},{"d":"2016-07-16","p":"2013ANAM01","v":27886,"c":"NacionalPerubik2016"},{"d":"2016-08-13","p":"2014ZARA01","v":37643,"c":"GameProTour2016"},{"d":"2016-08-13","p":"2013BERD02","v":39197,"c":"GameProTour2016"},{"d":"2016-08-13","p":"2015SUCL01","v":41608,"c":"GameProTour2016"},{"d":"2016-09-03","p":"2015VASQ06","v":38853,"c":"YoRubik2016"},{"d":"2016-10-29","p":"2014ZARA01","v":31984,"c":"TaiwanChampionship2016"},{"d":"2017-01-27","p":"2016SANC08","v":57063,"c":"SantaCruzRubiksChallengue2017"},{"d":"2017-02-04","p":"2015VASQ06","v":26980,"c":"AventuraCubicaIII2017"},{"d":"2017-02-04","p":"2015TELL01","v":15840,"c":"AventuraCubicaIII2017"},{"d":"2017-04-30","p":"2016SANC08","v":44605,"c":"CopaRubikSimonIPatino2017"},{"d":"2017-06-17","p":"2011CUBA02","v":19948,"c":"LatinAmericaCubingTourCochab2017"},{"d":"2017-06-17","p":"2016SANC08","v":41997,"c":"LatinAmericaCubingTourCochab2017"},{"d":"2017-06-24","p":"2011CUBA02","v":19657,"c":"LatinAmericaCubingTourLima2017"},{"d":"2017-06-24","p":"2015VASQ06","v":24481,"c":"LatinAmericaCubingTourLima2017"},{"d":"2017-06-24","p":"2016SANC08","v":35501,"c":"LatinAmericaCubingTourLima2017"},{"d":"2017-06-24","p":"2015TELL01","v":14794,"c":"LatinAmericaCubingTourLima2017"},{"d":"2017-07-22","p":"2015VASQ06","v":23399,"c":"LTCCubeFest2017"},{"d":"2017-07-22","p":"2014RUIZ10","v":22853,"c":"LTCCubeFest2017"},{"d":"2017-08-26","p":"2013VALD02","v":19909,"c":"CampeonatoNacionalPerubik2017"},{"d":"2017-08-26","p":"2011CUBA02","v":18346,"c":"CampeonatoNacionalPerubik2017"},{"d":"2017-08-26","p":"2015VASQ06","v":22328,"c":"CampeonatoNacionalPerubik2017"},{"d":"2017-08-26","p":"2015FELI01","v":29742,"c":"CampeonatoNacionalPerubik2017"},{"d":"2017-11-04","p":"2016SANC08","v":33588,"c":"YoRubik20SC2017"},{"d":"2017-12-16","p":"2015TELL01","v":14091,"c":"CrazyCubesChristmas2017"},{"d":"2017-12-16","p":"2016OBRE01","v":32301,"c":"CrazyCubesChristmas2017"},{"d":"2018-01-13","p":"2016SANC08","v":30328,"c":"EkekoRubik2018"},{"d":"2018-01-27","p":"2016BECE01","v":20501,"c":"UnivalleBigCubes2018"},{"d":"2018-01-27","p":"2017RODR25","v":29485,"c":"AventuraCubicaV2018"},{"d":"2018-01-27","p":"2016ELIA02","v":27681,"c":"AventuraCubicaV2018"},{"d":"2018-01-27","p":"2013TEMP01","v":26025,"c":"AventuraCubicaV2018"},{"d":"2018-01-27","p":"2015ACHA01","v":28083,"c":"AventuraCubicaV2018"},{"d":"2018-01-27","p":"2016OBRE01","v":32088,"c":"AventuraCubicaV2018"},{"d":"2018-03-10","p":"2017DIBA01","v":25023,"c":"SanJoseCubing2018"},{"d":"2018-03-10","p":"2013TEMP01","v":25024,"c":"SanJoseCubing2018"},{"d":"2018-03-10","p":"2016VARG04","v":24434,"c":"SanJoseCubing2018"},{"d":"2018-03-10","p":"2017FLOR01","v":27252,"c":"SanJoseCubing2018"},{"d":"2018-03-10","p":"2017AGUI15","v":22103,"c":"SanJoseCubing2018"},{"d":"2018-03-10","p":"2015TELL01","v":13214,"c":"SanJoseCubing2018"},{"d":"2018-03-10","p":"2015FELI01","v":26209,"c":"SanJoseCubing2018"},{"d":"2018-04-21","p":"2017RODR25","v":22804,"c":"FIGHTPeru2018"},{"d":"2018-04-21","p":"2013TEMP01","v":23931,"c":"FIGHTPeru2018"},{"d":"2018-04-21","p":"2015FELI01","v":25913,"c":"FIGHTPeru2018"},{"d":"2018-05-19","p":"2017HUAN07","v":26040,"c":"TorneoActivaClub2018"},{"d":"2018-05-19","p":"2017DELG02","v":41145,"c":"TorneoActivaClub2018"},{"d":"2018-05-19","p":"2015FELI01","v":24475,"c":"TorneoActivaClub2018"},{"d":"2018-06-29","p":"2016RODR37","v":30737,"c":"PeruNationals2018"},{"d":"2018-06-29","p":"2017HUAN07","v":23857,"c":"PeruNationals2018"},{"d":"2018-06-29","p":"2018LAUR02","v":25892,"c":"PeruNationals2018"},{"d":"2018-06-29","p":"2015FELI01","v":24206,"c":"PeruNationals2018"},{"d":"2018-07-05","p":"2016SANC08","v":27319,"c":"BoliviaNationals2018"},{"d":"2018-08-04","p":"2016SANC08","v":25434,"c":"CochaCubingI2018"},{"d":"2018-09-29","p":"2017DIBA01","v":23042,"c":"SalesianosOpen2018"},{"d":"2018-09-29","p":"2015SUCL01","v":29634,"c":"SalesianosOpen2018"},{"d":"2018-09-29","p":"2014ZARA01","v":30729,"c":"SalesianosOpen2018"},{"d":"2018-09-29","p":"2016BECE01","v":19052,"c":"SalesianosOpen2018"},{"d":"2018-10-20","p":"2016RODR37","v":25552,"c":"AventuraCubicaVI2018"},{"d":"2018-10-20","p":"2016OBRE01","v":25903,"c":"AventuraCubicaVI2018"},{"d":"2018-10-20","p":"2018LAUR02","v":23387,"c":"AventuraCubicaVI2018"},{"d":"2018-10-20","p":"2016NUNE15","v":25128,"c":"AventuraCubicaVI2018"},{"d":"2018-11-03","p":"2017SALA07","v":38575,"c":"IquitosCubing2018"},{"d":"2019-01-12","p":"2017DIBA01","v":21988,"c":"TCGDeluxe2019"},{"d":"2019-01-12","p":"2017AGUI15","v":15699,"c":"TCGDeluxe2019"},{"d":"2019-01-12","p":"2016OBRE01","v":25749,"c":"TCGDeluxe2019"},{"d":"2019-01-26","p":"2016SANC08","v":24337,"c":"SanRafaelSummer2019"},{"d":"2019-02-16","p":"2018LAUR02","v":19952,"c":"AventuraCubicaVII2019"},{"d":"2019-02-16","p":"2015FELI01","v":23409,"c":"AventuraCubicaVII2019"},{"d":"2019-02-16","p":"2019JAMB01","v":24829,"c":"AventuraCubicaVII2019"},{"d":"2019-02-16","p":"2017DELG02","v":24424,"c":"AventuraCubicaVII2019"},{"d":"2019-04-20","p":"2018LAUR02","v":19762,"c":"SpeedcuberPeruOtono2019"},{"d":"2019-04-20","p":"2014RUIZ10","v":20443,"c":"SpeedcuberPeruOtono2019"},{"d":"2019-04-20","p":"2016RODR37","v":23640,"c":"SpeedcuberPeruOtono2019"},{"d":"2019-07-12","p":"2016SANC08","v":23547,"c":"UnifranzSantaCruz2019"},{"d":"2019-08-10","p":"2017AGUI15","v":14104,"c":"PreNacionalesArequipa2019"},{"d":"2019-08-16","p":"2018LAUR02","v":19288,"c":"PeruNationals2019"},{"d":"2019-08-16","p":"2016RODR37","v":22641,"c":"PeruNationals2019"},{"d":"2019-08-16","p":"2016OBRE01","v":24517,"c":"PeruNationals2019"},{"d":"2019-08-16","p":"2018QUIJ01","v":24751,"c":"PeruNationals2019"},{"d":"2019-08-16","p":"2017DELG02","v":24060,"c":"PeruNationals2019"},{"d":"2019-09-28","p":"2018LAUR02","v":18060,"c":"ComasSpeedsolving2019"},{"d":"2019-09-28","p":"2018QUIJ01","v":23495,"c":"ComasSpeedsolving2019"},{"d":"2019-09-28","p":"2013TEMP01","v":23829,"c":"ComasSpeedsolving2019"},{"d":"2019-09-28","p":"2017DELG02","v":22966,"c":"ComasSpeedsolving2019"},{"d":"2019-09-28","p":"2017REYE27","v":25230,"c":"ComasSpeedsolving2019"},{"d":"2019-09-28","p":"2019ALLC01","v":38016,"c":"ComasSpeedsolving2019"},{"d":"2019-09-29","p":"2016SANC08","v":23163,"c":"UnifranzSpringCubingFest2019"},{"d":"2019-12-06","p":"2016SANC08","v":22115,"c":"BoliviaNationals2019"},{"d":"2019-12-14","p":"2015SUCL01","v":22024,"c":"TCGSpring2019"},{"d":"2019-12-14","p":"2019TORI04","v":34237,"c":"TCGSpring2019"},{"d":"2019-12-21","p":"2016SANC08","v":20225,"c":"UnifranzElAlto2019"},{"d":"2020-02-29","p":"2016MILL07","v":19098,"c":"ARomperTuPBLima2020"},{"d":"2020-02-29","p":"2019JAMB01","v":20472,"c":"ARomperTuPBLima2020"},{"d":"2020-02-29","p":"2017DELG02","v":21984,"c":"ARomperTuPBLima2020"},{"d":"2020-02-29","p":"2017SALA07","v":26464,"c":"ARomperTuPBLima2020"},{"d":"2020-02-29","p":"2019ALLC01","v":33304,"c":"ARomperTuPBLima2020"},{"d":"2022-03-12","p":"2018LAUR02","v":17564,"c":"LimaCuberano2022"},{"d":"2022-03-12","p":"2017HUAN07","v":17385,"c":"LimaCuberano2022"},{"d":"2022-03-12","p":"2017SALA07","v":21379,"c":"LimaCuberano2022"},{"d":"2022-03-12","p":"2018QUIJ01","v":21803,"c":"LimaCuberano2022"},{"d":"2022-03-12","p":"2017REYE27","v":22485,"c":"LimaCuberano2022"},{"d":"2022-03-12","p":"2018OCHO03","v":23518,"c":"LimaCuberano2022"},{"d":"2022-04-30","p":"2018LAUR02","v":16952,"c":"TCGNuevaGeneracion2022"},{"d":"2022-04-30","p":"2017HUAN07","v":15881,"c":"TCGNuevaGeneracion2022"},{"d":"2022-04-30","p":"2016MILL07","v":17374,"c":"TCGNuevaGeneracion2022"},{"d":"2022-04-30","p":"2014RUIZ10","v":17728,"c":"TCGNuevaGeneracion2022"},{"d":"2022-04-30","p":"2017DELG02","v":19605,"c":"TCGNuevaGeneracion2022"},{"d":"2022-04-30","p":"2017REYE27","v":21358,"c":"TCGNuevaGeneracion2022"},{"d":"2022-04-30","p":"2019ALLC01","v":22862,"c":"TCGNuevaGeneracion2022"},{"d":"2022-04-30","p":"2016OBRE01","v":23725,"c":"TCGNuevaGeneracion2022"},{"d":"2022-07-02","p":"2017HUAN07","v":14946,"c":"SchoolWinterLima2022"},{"d":"2022-07-02","p":"2018LAUR02","v":15718,"c":"SchoolWinterLima2022"},{"d":"2022-07-02","p":"2019ALLC01","v":21844,"c":"SchoolWinterLima2022"},{"d":"2022-07-02","p":"2016OBRE01","v":23323,"c":"SchoolWinterLima2022"},{"d":"2022-08-06","p":"2014RUIZ10","v":17613,"c":"RealCube2022"},{"d":"2022-08-06","p":"2017REYE27","v":19964,"c":"RealCube2022"},{"d":"2022-08-06","p":"2019ALLC01","v":19956,"c":"RealCube2022"},{"d":"2022-08-19","p":"2017QUIS11","v":19450,"c":"PeruNationals2022"},{"d":"2022-08-19","p":"2019TORI04","v":19475,"c":"PeruNationals2022"},{"d":"2022-08-19","p":"2018OCHO03","v":21473,"c":"PeruNationals2022"},{"d":"2022-12-03","p":"2018OCHO03","v":18168,"c":"TCGPowerUp2022"},{"d":"2022-12-03","p":"2017REYE27","v":19963,"c":"TCGPowerUp2022"},{"d":"2022-12-03","p":"2014RUIZ10","v":17237,"c":"TCGPowerUp2022"},{"d":"2022-12-10","p":"2015VASQ06","v":20848,"c":"UtahSnowballBash2022"},{"d":"2023-01-14","p":"2015VASQ06","v":20103,"c":"IdahoFreezeDried2023"},{"d":"2023-02-04","p":"2018LAUR02","v":15344,"c":"LimaSummer2023"},{"d":"2023-02-04","p":"2018OCHO03","v":17731,"c":"LimaSummer2023"},{"d":"2023-02-04","p":"2014RUIZ10","v":16346,"c":"LimaSummer2023"},{"d":"2023-02-04","p":"2016OBRE01","v":20712,"c":"LimaSummer2023"},{"d":"2023-02-04","p":"2020CABE02","v":20040,"c":"LimaSummer2023"},{"d":"2023-04-15","p":"2017AGUI15","v":13715,"c":"UNSASpeedcubingOtono2023"},{"d":"2023-04-15","p":"2016MILL07","v":16795,"c":"UNSASpeedcubingOtono2023"},{"d":"2023-05-20","p":"2017SALA07","v":18165,"c":"CubeForceLima2023"},{"d":"2023-05-20","p":"2019ALLC01","v":18109,"c":"CubeForceLima2023"},{"d":"2023-05-20","p":"2020CABE02","v":19683,"c":"CubeForceLima2023"},{"d":"2023-07-22","p":"2017HUAN07","v":14305,"c":"LimaCubinvierno2023"},{"d":"2023-07-22","p":"2018LAUR02","v":14276,"c":"LimaCubinvierno2023"},{"d":"2023-07-22","p":"2016OBRE01","v":20363,"c":"LimaCubinvierno2023"},{"d":"2023-08-04","p":"2015TELL01","v":12909,"c":"PeruNationals2023"},{"d":"2023-08-04","p":"2017SALA07","v":17749,"c":"PeruNationals2023"},{"d":"2023-08-04","p":"2017REYE27","v":19392,"c":"PeruNationals2023"},{"d":"2023-08-04","p":"2015SUCL01","v":21631,"c":"PeruNationals2023"},{"d":"2023-08-12","p":"2016MILL07","v":16222,"c":"SanMarcosOpen2023"},{"d":"2023-08-12","p":"2020CABE02","v":18521,"c":"SanMarcosOpen2023"},{"d":"2023-08-12","p":"2016RODR37","v":19502,"c":"SanMarcosOpen2023"},{"d":"2023-08-19","p":"2014RUIZ10","v":16267,"c":"LaTiendaCuberaFest2023"},{"d":"2023-08-19","p":"2018OCHO03","v":17535,"c":"LaTiendaCuberaFest2023"},{"d":"2023-08-19","p":"2017DELG02","v":19328,"c":"LaTiendaCuberaFest2023"},{"d":"2023-09-03","p":"2017REYE27","v":19353,"c":"ChosicaCubingCup2023"},{"d":"2023-09-16","p":"2017HUAN07","v":14210,"c":"PlazaCenterCubeLimaI2023"},{"d":"2023-09-16","p":"2016MILL07","v":16166,"c":"PlazaCenterCubeLimaI2023"},{"d":"2023-09-16","p":"2014RUIZ10","v":16229,"c":"PlazaCenterCubeLimaI2023"},{"d":"2023-09-16","p":"2017REYE27","v":18090,"c":"PlazaCenterCubeLimaI2023"},{"d":"2023-09-30","p":"2015ACHA01","v":22657,"c":"PlazaCenterCubeLimaII2023"},{"d":"2023-12-16","p":"2016MILL07","v":15777,"c":"SpeedcuberPeruIILima2023"},{"d":"2023-12-16","p":"2018OCHO03","v":16702,"c":"SpeedcuberPeruIILima2023"},{"d":"2023-12-16","p":"2017REYE27","v":17812,"c":"SpeedcuberPeruIILima2023"},{"d":"2024-01-14","p":"2018LAUR02","v":13963,"c":"ChosicasBigShow2024"},{"d":"2024-01-14","p":"2017HUAN07","v":14045,"c":"ChosicasBigShow2024"},{"d":"2024-01-14","p":"2018OCHO03","v":16573,"c":"ChosicasBigShow2024"},{"d":"2024-01-14","p":"2017SALA07","v":16810,"c":"ChosicasBigShow2024"},{"d":"2024-01-14","p":"2017DELG02","v":18148,"c":"ChosicasBigShow2024"},{"d":"2024-01-14","p":"2018QUIJ01","v":18290,"c":"ChosicasBigShow2024"},{"d":"2024-01-14","p":"2016RODR37","v":18430,"c":"ChosicasBigShow2024"},{"d":"2024-02-10","p":"2017DELG02","v":17232,"c":"PlazaCenterCubeLimalll2024"},{"d":"2024-02-10","p":"2015FELI01","v":22937,"c":"PlazaCenterCubeLimalll2024"},{"d":"2024-05-04","p":"2018QUIJ01","v":17741,"c":"ChambeaenTuPBLima2024"},{"d":"2024-07-19","p":"2018LAUR02","v":13865,"c":"OpenPUCPCubingCommunity2024"},{"d":"2024-07-19","p":"2018OCHO03","v":15553,"c":"OpenPUCPCubingCommunity2024"},{"d":"2024-08-31","p":"2010MOND01","v":43136,"c":"ValdAranOpen2024"},{"d":"2024-10-08","p":"2016MILL07","v":15769,"c":"CaballerodelosMaresLima2024"},{"d":"2024-11-22","p":"2018OCHO03","v":15471,"c":"PeruNationals2024"},{"d":"2024-11-22","p":"2017REYE27","v":17346,"c":"PeruNationals2024"},{"d":"2024-11-22","p":"2023ROJA17","v":21612,"c":"PeruNationals2024"},{"d":"2025-01-25","p":"2017DELG02","v":16891,"c":"LosReyesdelCuboChiclayoIII2025"},{"d":"2025-01-25","p":"2022NUNU03","v":21093,"c":"LosReyesdelCuboChiclayoIII2025"},{"d":"2025-02-22","p":"2017HUAN07","v":13951,"c":"PUCPCubingFestivalIV2025"},{"d":"2025-02-22","p":"2016MILL07","v":15110,"c":"PUCPCubingFestivalIV2025"},{"d":"2025-02-22","p":"2022NUNU03","v":18944,"c":"PUCPCubingFestivalIV2025"},{"d":"2025-05-03","p":"2010MOND01","v":42435,"c":"ValldeNuria2025"},{"d":"2025-07-19","p":"2017RODR25","v":17686,"c":"PUCPCubingFestivalV2025"},{"d":"2025-07-19","p":"2022NUNU03","v":18596,"c":"PUCPCubingFestivalV2025"},{"d":"2025-07-19","p":"2018OCHO03","v":14963,"c":"PUCPCubingFestivalV2025"},{"d":"2025-07-19","p":"2014RUIZ10","v":16091,"c":"PUCPCubingFestivalV2025"},{"d":"2025-07-19","p":"2018LAUR02","v":12962,"c":"PUCPCubingFestivalV2025"},{"d":"2025-07-19","p":"2016MILL07","v":15007,"c":"PUCPCubingFestivalV2025"},{"d":"2025-08-24","p":"2014RUIZ10","v":15938,"c":"PUCPCubingFestivalVI2025"},{"d":"2025-08-24","p":"2023CHUG02","v":21489,"c":"PUCPCubingFestivalVI2025"},{"d":"2025-08-24","p":"2016MILL07","v":14438,"c":"PUCPCubingFestivalVI2025"},{"d":"2025-08-24","p":"2017REYE27","v":16950,"c":"PUCPCubingFestivalVI2025"},{"d":"2025-08-29","p":"2023ROJA17","v":17500,"c":"PeruNationals2025"},{"d":"2025-08-29","p":"2022NUNU03","v":18401,"c":"PeruNationals2025"},{"d":"2025-08-29","p":"2017HUAN07","v":13482,"c":"PeruNationals2025"},{"d":"2025-08-29","p":"2015SUCL01","v":19244,"c":"PeruNationals2025"},{"d":"2025-08-29","p":"2018OCHO03","v":14304,"c":"PeruNationals2025"},{"d":"2025-10-10","p":"2016SANC08","v":20192,"c":"SantaCruzNxN2025"},{"d":"2025-10-19","p":"2023CHUG02","v":19909,"c":"PUCPCubingFestivalVII2025"},{"d":"2025-10-19","p":"2016OBRE01","v":19575,"c":"PUCPCubingFestivalVII2025"},{"d":"2025-11-29","p":"2015VASQ06","v":20044,"c":"UtahChampionship2025"},{"d":"2025-12-07","p":"2023CHUG02","v":19374,"c":"PUCPCubingFestivalVIII2025"},{"d":"2025-12-07","p":"2022NUNU03","v":17570,"c":"PUCPCubingFestivalVIII2025"},{"d":"2025-12-07","p":"2018OCHO03","v":13683,"c":"PUCPCubingFestivalVIII2025"},{"d":"2025-12-13","p":"2024PALO06","v":17357,"c":"ArmandoSuenosBlenkir2025"},{"d":"2025-12-13","p":"2017HUAN07","v":13434,"c":"ArmandoSuenosBlenkir2025"},{"d":"2025-12-13","p":"2016MILL07","v":14413,"c":"ArmandoSuenosBlenkir2025"},{"d":"2025-12-13","p":"2018QUIJ01","v":17593,"c":"ArmandoSuenosBlenkir2025"},{"d":"2025-12-13","p":"2017SALA07","v":16480,"c":"ArmandoSuenosBlenkir2025"},{"d":"2025-12-20","p":"2016SANC08","v":19744,"c":"MYHMBoliviaNationals2025"},{"d":"2026-01-23","p":"2017HUAN07","v":13402,"c":"SteelsCubesLima2026"},{"d":"2026-01-23","p":"2016OBRE01","v":19518,"c":"SteelsCubesLima2026"},{"d":"2026-01-23","p":"2016RODR37","v":17635,"c":"SteelsCubesLima2026"},{"d":"2026-02-21","p":"2015VASQ06","v":19206,"c":"CubingwithDinosaursLehi2026"},{"d":"2026-02-28","p":"2018QUIJ01","v":17185,"c":"SummeroftheCubeHuancayo2026"},{"d":"2026-03-07","p":"2017HUAN07","v":12138,"c":"PUCPCubingFestivalIX2026"},{"d":"2026-03-07","p":"2016OBRE01","v":19392,"c":"PUCPCubingFestivalIX2026"},{"d":"2026-03-07","p":"2023CHUG02","v":18995,"c":"PUCPCubingFestivalIX2026"},{"d":"2026-03-21","p":"2018OCHO03","v":13144,"c":"PUCPCubingFestivalX2026"},{"d":"2026-03-21","p":"2023CHUG02","v":16816,"c":"PUCPCubingFestivalX2026"},{"d":"2026-03-28","p":"2016SANC08","v":19654,"c":"UnicenOpenSCZ2026"}],"single_r":[{"d":"2011-12-16","p":"2010MOND01","v":76000,"c":"SpanishChampionship2011"},{"d":"2012-01-26","p":"2010MOND01","v":73900,"c":"BarcelonaWinterOpen2012"},{"d":"2013-01-05","p":"2011QUEZ01","v":44013,"c":"CampeonatoSudamericano2013"},{"d":"2013-01-05","p":"2011ARAN01","v":59374,"c":"CampeonatoSudamericano2013"},{"d":"2013-02-22","p":"2010MOND01","v":67800,"c":"UAMOpen2013"},{"d":"2013-03-16","p":"2011ARAN01","v":49204,"c":"ArequipaSummer2013"},{"d":"2013-04-05","p":"2011LUJA01","v":35769,"c":"NacionalPerubik2013"},{"d":"2013-04-05","p":"2011QUEZ01","v":43527,"c":"NacionalPerubik2013"},{"d":"2013-04-05","p":"2013VALD02","v":43980,"c":"NacionalPerubik2013"},{"d":"2013-07-20","p":"2013VALD02","v":31747,"c":"TrujilloOpen2013"},{"d":"2013-07-20","p":"2012ROBL01","v":36031,"c":"TrujilloOpen2013"},{"d":"2013-07-20","p":"2011LUJA01","v":41366,"c":"TrujilloOpen2013"},{"d":"2013-10-04","p":"2011ARAN01","v":38657,"c":"MarianoMelgar2013"},{"d":"2013-10-04","p":"2011CUBA02","v":45054,"c":"MarianoMelgar2013"},{"d":"2013-10-26","p":"2012ROBL01","v":29839,"c":"PalacioDelCubo2013"},{"d":"2013-10-26","p":"2013CAST06","v":30173,"c":"PalacioDelCubo2013"},{"d":"2013-10-26","p":"2011QUEZ01","v":36670,"c":"PalacioDelCubo2013"},{"d":"2013-10-26","p":"2011CUBA02","v":44798,"c":"PalacioDelCubo2013"},{"d":"2013-10-26","p":"2011CORA01","v":45747,"c":"PalacioDelCubo2013"},{"d":"2014-02-07","p":"2013VALD02","v":25836,"c":"CulturalOpen2014"},{"d":"2014-02-07","p":"2011CUBA02","v":44217,"c":"CulturalOpen2014"},{"d":"2014-03-08","p":"2013VALD02","v":23898,"c":"BackToThePalace2014"},{"d":"2014-03-08","p":"2013CAST06","v":25386,"c":"BackToThePalace2014"},{"d":"2014-03-08","p":"2012ROBL01","v":31209,"c":"BackToThePalace2014"},{"d":"2014-03-08","p":"2011QUEZ01","v":42194,"c":"BackToThePalace2014"},{"d":"2014-03-08","p":"2011CUBA02","v":42409,"c":"BackToThePalace2014"},{"d":"2014-06-20","p":"2011CUBA02","v":39591,"c":"UniRubik2014"},{"d":"2014-07-12","p":"2013VALD02","v":25149,"c":"MarianoMelgar2014"},{"d":"2014-07-12","p":"2011CUBA02","v":38690,"c":"MarianoMelgar2014"},{"d":"2014-09-06","p":"2011QUEZ01","v":34425,"c":"TCGLima2014"},{"d":"2014-10-24","p":"2011CUBA02","v":36589,"c":"IIOpenArguedas2014"},{"d":"2014-10-24","p":"2013VERA03","v":38561,"c":"IIOpenArguedas2014"},{"d":"2015-01-31","p":"2015TELL01","v":23241,"c":"NewAvgeOpen2015"},{"d":"2015-01-31","p":"2013HUAN30","v":32720,"c":"NewAvgeOpen2015"},{"d":"2015-06-13","p":"2015TELL01","v":20400,"c":"HunterOpen2015"},{"d":"2015-06-13","p":"2011CUBA02","v":24837,"c":"HunterOpen2015"},{"d":"2015-07-08","p":"2015TELL01","v":20670,"c":"TCGAndFriendsAQP2015"},{"d":"2015-07-08","p":"2013HUAN03","v":34072,"c":"TCGAndFriendsAQP2015"},{"d":"2015-07-11","p":"2015TELL01","v":21131,"c":"TCGAndFriends2015"},{"d":"2015-07-11","p":"2014GUTI04","v":31382,"c":"TCGAndFriends2015"},{"d":"2015-07-17","p":"2015TELL01","v":19159,"c":"WC2015"},{"d":"2015-07-17","p":"2015TELL01","v":20363,"c":"WC2015"},{"d":"2015-09-26","p":"2011CUBA02","v":24975,"c":"CochabambaOpen2015"},{"d":"2016-01-23","p":"2015TELL01","v":18803,"c":"TorneoAventuraCubica2016"},{"d":"2016-01-23","p":"2014CORD04","v":29375,"c":"TorneoAventuraCubica2016"},{"d":"2016-02-12","p":"2011CUBA02","v":20638,"c":"UchiMontevideo2016"},{"d":"2016-02-12","p":"2011CUBA02","v":20922,"c":"UchiMontevideo2016"},{"d":"2016-03-20","p":"2015TELL01","v":16920,"c":"CrazyCubesSummer2016"},{"d":"2016-03-20","p":"2013VALD02","v":23760,"c":"CrazyCubesSummer2016"},{"d":"2016-06-04","p":"2015TELL01","v":21791,"c":"TorneoCosmocentro2016"},{"d":"2016-07-01","p":"2015TELL01","v":18549,"c":"BoliviaNationals2016"},{"d":"2016-07-01","p":"2015TELL01","v":18724,"c":"BoliviaNationals2016"},{"d":"2016-07-01","p":"2011CUBA02","v":20179,"c":"BoliviaNationals2016"},{"d":"2016-07-01","p":"2011CUBA02","v":22596,"c":"BoliviaNationals2016"},{"d":"2016-07-16","p":"2015TELL01","v":18968,"c":"NacionalPerubik2016"},{"d":"2016-08-13","p":"2015TELL01","v":19238,"c":"GameProTour2016"},{"d":"2017-02-04","p":"2015TELL01","v":15840,"c":"AventuraCubicaIII2017"},{"d":"2017-06-17","p":"2011CUBA02","v":19948,"c":"LatinAmericaCubingTourCochab2017"},{"d":"2017-06-24","p":"2015TELL01","v":14794,"c":"LatinAmericaCubingTourLima2017"},{"d":"2017-06-24","p":"2011CUBA02","v":19657,"c":"LatinAmericaCubingTourLima2017"},{"d":"2017-07-22","p":"2015TELL01","v":15458,"c":"LTCCubeFest2017"},{"d":"2017-08-26","p":"2015TELL01","v":16048,"c":"CampeonatoNacionalPerubik2017"},{"d":"2017-08-26","p":"2011CUBA02","v":18346,"c":"CampeonatoNacionalPerubik2017"},{"d":"2017-08-26","p":"2013VALD02","v":19909,"c":"CampeonatoNacionalPerubik2017"},{"d":"2017-12-16","p":"2015TELL01","v":14091,"c":"CrazyCubesChristmas2017"},{"d":"2018-01-27","p":"2015TELL01","v":15565,"c":"AventuraCubicaV2018"},{"d":"2018-03-10","p":"2015TELL01","v":13214,"c":"SanJoseCubing2018"},{"d":"2018-04-21","p":"2015TELL01","v":13356,"c":"FIGHTPeru2018"},{"d":"2018-05-19","p":"2015TELL01","v":14957,"c":"TorneoActivaClub2018"},{"d":"2018-06-29","p":"2015TELL01","v":15303,"c":"PeruNationals2018"},{"d":"2018-07-19","p":"2015TELL01","v":13996,"c":"Euro2018"},{"d":"2018-07-19","p":"2015TELL01","v":15454,"c":"Euro2018"},{"d":"2018-10-20","p":"2015TELL01","v":14877,"c":"AventuraCubicaVI2018"},{"d":"2018-11-03","p":"2015TELL01","v":15022,"c":"IquitosCubing2018"},{"d":"2018-12-15","p":"2015TELL01","v":15786,"c":"SouthAmericanChampionship2018"},{"d":"2019-01-12","p":"2017AGUI15","v":15699,"c":"TCGDeluxe2019"},{"d":"2019-08-10","p":"2017AGUI15","v":14104,"c":"PreNacionalesArequipa2019"},{"d":"2019-08-16","p":"2015TELL01","v":13633,"c":"PeruNationals2019"},{"d":"2019-09-28","p":"2015TELL01","v":14813,"c":"ComasSpeedsolving2019"},{"d":"2019-12-14","p":"2017AGUI15","v":14586,"c":"TCGSpring2019"},{"d":"2022-07-02","p":"2017HUAN07","v":14946,"c":"SchoolWinterLima2022"},{"d":"2022-08-19","p":"2017HUAN07","v":15398,"c":"PeruNationals2022"},{"d":"2023-02-04","p":"2018LAUR02","v":15344,"c":"LimaSummer2023"},{"d":"2023-04-15","p":"2017AGUI15","v":13715,"c":"UNSASpeedcubingOtono2023"},{"d":"2023-05-20","p":"2017HUAN07","v":15030,"c":"CubeForceLima2023"},{"d":"2023-07-22","p":"2018LAUR02","v":14276,"c":"LimaCubinvierno2023"},{"d":"2023-07-22","p":"2017HUAN07","v":14305,"c":"LimaCubinvierno2023"},{"d":"2023-07-22","p":"2015TELL01","v":14619,"c":"LimaCubinvierno2023"},{"d":"2023-08-04","p":"2015TELL01","v":12909,"c":"PeruNationals2023"},{"d":"2023-08-04","p":"2017HUAN07","v":14510,"c":"PeruNationals2023"},{"d":"2023-08-12","p":"2015TELL01","v":13981,"c":"SanMarcosOpen2023"},{"d":"2023-08-19","p":"2015TELL01","v":13906,"c":"LaTiendaCuberaFest2023"},{"d":"2023-09-03","p":"2015TELL01","v":14513,"c":"ChosicaCubingCup2023"},{"d":"2023-09-03","p":"2017HUAN07","v":14581,"c":"ChosicaCubingCup2023"},{"d":"2023-09-16","p":"2017HUAN07","v":14210,"c":"PlazaCenterCubeLimaI2023"},{"d":"2023-09-16","p":"2018LAUR02","v":14465,"c":"PlazaCenterCubeLimaI2023"},{"d":"2023-09-30","p":"2015TELL01","v":14320,"c":"PlazaCenterCubeLimaII2023"},{"d":"2023-11-04","p":"2015TELL01","v":14127,"c":"RealGeekcuberPucallpa2023"},{"d":"2024-01-14","p":"2015TELL01","v":13552,"c":"ChosicasBigShow2024"},{"d":"2024-01-14","p":"2018LAUR02","v":13963,"c":"ChosicasBigShow2024"},{"d":"2024-01-14","p":"2018LAUR02","v":14011,"c":"ChosicasBigShow2024"},{"d":"2024-01-14","p":"2017HUAN07","v":14045,"c":"ChosicasBigShow2024"},{"d":"2024-03-02","p":"2015TELL01","v":13570,"c":"PlazaCenterCubeLimaIV2024"},{"d":"2024-05-04","p":"2015TELL01","v":13966,"c":"ChambeaenTuPBLima2024"},{"d":"2024-07-19","p":"2018LAUR02","v":13865,"c":"OpenPUCPCubingCommunity2024"},{"d":"2025-02-22","p":"2018LAUR02","v":13871,"c":"PUCPCubingFestivalIV2025"},{"d":"2025-02-22","p":"2017HUAN07","v":13951,"c":"PUCPCubingFestivalIV2025"},{"d":"2025-07-19","p":"2018LAUR02","v":12962,"c":"PUCPCubingFestivalV2025"},{"d":"2025-08-29","p":"2017HUAN07","v":13482,"c":"PeruNationals2025"},{"d":"2025-08-29","p":"2018LAUR02","v":13740,"c":"PeruNationals2025"},{"d":"2025-08-29","p":"2017HUAN07","v":13906,"c":"PeruNationals2025"},{"d":"2025-12-07","p":"2018OCHO03","v":13683,"c":"PUCPCubingFestivalVIII2025"},{"d":"2025-12-13","p":"2017HUAN07","v":13434,"c":"ArmandoSuenosBlenkir2025"},{"d":"2026-01-23","p":"2017HUAN07","v":13402,"c":"SteelsCubesLima2026"},{"d":"2026-02-28","p":"2017HUAN07","v":13507,"c":"SummeroftheCubeHuancayo2026"},{"d":"2026-03-07","p":"2017HUAN07","v":12138,"c":"PUCPCubingFestivalIX2026"},{"d":"2026-03-21","p":"2017HUAN07","v":12928,"c":"PUCPCubingFestivalX2026"},{"d":"2026-03-21","p":"2018OCHO03","v":13144,"c":"PUCPCubingFestivalX2026"},{"d":"2026-06-12","p":"2017HUAN07","v":13613,"c":"SAC2026"}],"average":[{"d":"2013-01-05","p":"2011QUEZ01","v":49213,"c":"CampeonatoSudamericano2013"},{"d":"2013-04-05","p":"2011LUJA01","v":36668,"c":"NacionalPerubik2013"},{"d":"2013-04-05","p":"2011QUEZ01","v":44688,"c":"NacionalPerubik2013"},{"d":"2013-04-05","p":"2013VALD02","v":44724,"c":"NacionalPerubik2013"},{"d":"2013-07-20","p":"2013VALD02","v":35463,"c":"TrujilloOpen2013"},{"d":"2013-07-20","p":"2012ROBL01","v":36992,"c":"TrujilloOpen2013"},{"d":"2013-10-04","p":"2011ARAN01","v":40605,"c":"MarianoMelgar2013"},{"d":"2013-10-04","p":"2011CUBA02","v":45931,"c":"MarianoMelgar2013"},{"d":"2013-10-26","p":"2013CAST06","v":30931,"c":"PalacioDelCubo2013"},{"d":"2013-10-26","p":"2012ROBL01","v":31320,"c":"PalacioDelCubo2013"},{"d":"2013-10-26","p":"2011QUEZ01","v":41681,"c":"PalacioDelCubo2013"},{"d":"2013-10-26","p":"2011CORA01","v":51046,"c":"PalacioDelCubo2013"},{"d":"2014-02-07","p":"2013VALD02","v":26525,"c":"CulturalOpen2014"},{"d":"2014-03-08","p":"2013VALD02","v":25383,"c":"BackToThePalace2014"},{"d":"2014-03-08","p":"2013CAST06","v":28938,"c":"BackToThePalace2014"},{"d":"2014-06-20","p":"2011CUBA02","v":40291,"c":"UniRubik2014"},{"d":"2014-07-12","p":"2013HUAN03","v":45641,"c":"MarianoMelgar2014"},{"d":"2014-07-12","p":"2013VALD02","v":25250,"c":"MarianoMelgar2014"},{"d":"2014-09-06","p":"2011QUEZ01","v":36154,"c":"TCGLima2014"},{"d":"2014-10-24","p":"2013VERA03","v":41650,"c":"IIOpenArguedas2014"},{"d":"2014-10-24","p":"2011CUBA02","v":36868,"c":"IIOpenArguedas2014"},{"d":"2014-11-29","p":"2013BERD02","v":43279,"c":"GameProTour2014"},{"d":"2015-01-31","p":"2013HUAN30","v":34854,"c":"NewAvgeOpen2015"},{"d":"2015-01-31","p":"2015TELL01","v":23614,"c":"NewAvgeOpen2015"},{"d":"2015-06-13","p":"2013HUAN03","v":38379,"c":"HunterOpen2015"},{"d":"2015-06-13","p":"2011CUBA02","v":26207,"c":"HunterOpen2015"},{"d":"2015-06-13","p":"2015TELL01","v":21890,"c":"HunterOpen2015"},{"d":"2015-07-08","p":"2013HUAN03","v":37107,"c":"TCGAndFriendsAQP2015"},{"d":"2015-07-11","p":"2015TELL01","v":21775,"c":"TCGAndFriends2015"},{"d":"2015-07-11","p":"2014GUTI04","v":34289,"c":"TCGAndFriends2015"},{"d":"2015-07-11","p":"2015ELIA03","v":41675,"c":"TCGAndFriends2015"},{"d":"2015-07-17","p":"2015TELL01","v":20892,"c":"WC2015"},{"d":"2016-01-23","p":"2015TELL01","v":19297,"c":"TorneoAventuraCubica2016"},{"d":"2016-01-23","p":"2014CORD04","v":32205,"c":"TorneoAventuraCubica2016"},{"d":"2016-01-23","p":"2013VERA03","v":35204,"c":"TorneoAventuraCubica2016"},{"d":"2016-02-12","p":"2011CUBA02","v":22536,"c":"UchiMontevideo2016"},{"d":"2016-03-20","p":"2015TELL01","v":18288,"c":"CrazyCubesSummer2016"},{"d":"2016-07-01","p":"2011CUBA02","v":20693,"c":"BoliviaNationals2016"},{"d":"2016-07-16","p":"2014RUIZ10","v":25610,"c":"NacionalPerubik2016"},{"d":"2016-07-16","p":"2014CORD04","v":27559,"c":"NacionalPerubik2016"},{"d":"2016-07-16","p":"2013ANAM01","v":31766,"c":"NacionalPerubik2016"},{"d":"2016-10-29","p":"2014ZARA01","v":34654,"c":"TaiwanChampionship2016"},{"d":"2017-02-04","p":"2015VASQ06","v":28137,"c":"AventuraCubicaIII2017"},{"d":"2017-02-04","p":"2015TELL01","v":16267,"c":"AventuraCubicaIII2017"},{"d":"2017-06-17","p":"2011CUBA02","v":20209,"c":"LatinAmericaCubingTourCochab2017"},{"d":"2017-06-24","p":"2015VASQ06","v":24952,"c":"LatinAmericaCubingTourLima2017"},{"d":"2017-06-24","p":"2015TELL01","v":15858,"c":"LatinAmericaCubingTourLima2017"},{"d":"2017-07-22","p":"2015VASQ06","v":24078,"c":"LTCCubeFest2017"},{"d":"2017-07-22","p":"2014RUIZ10","v":24390,"c":"LTCCubeFest2017"},{"d":"2017-08-26","p":"2013VALD02","v":20417,"c":"CampeonatoNacionalPerubik2017"},{"d":"2017-08-26","p":"2011CUBA02","v":18933,"c":"CampeonatoNacionalPerubik2017"},{"d":"2017-08-26","p":"2015VASQ06","v":23418,"c":"CampeonatoNacionalPerubik2017"},{"d":"2017-08-26","p":"2015FELI01","v":31256,"c":"CampeonatoNacionalPerubik2017"},{"d":"2017-12-16","p":"2015TELL01","v":14601,"c":"CrazyCubesChristmas2017"},{"d":"2017-12-16","p":"2016OBRE01","v":34326,"c":"CrazyCubesChristmas2017"},{"d":"2018-01-13","p":"2016SANC08","v":32893,"c":"EkekoRubik2018"},{"d":"2018-01-27","p":"2017RODR25","v":31468,"c":"AventuraCubicaV2018"},{"d":"2018-01-27","p":"2016ELIA02","v":28939,"c":"AventuraCubicaV2018"},{"d":"2018-01-27","p":"2013TEMP01","v":28057,"c":"AventuraCubicaV2018"},{"d":"2018-01-27","p":"2015ACHA01","v":28481,"c":"AventuraCubicaV2018"},{"d":"2018-03-10","p":"2017DIBA01","v":26472,"c":"SanJoseCubing2018"},{"d":"2018-03-10","p":"2013TEMP01","v":26974,"c":"SanJoseCubing2018"},{"d":"2018-03-10","p":"2016VARG04","v":26151,"c":"SanJoseCubing2018"},{"d":"2018-03-10","p":"2017AGUI15","v":23992,"c":"SanJoseCubing2018"},{"d":"2018-03-10","p":"2015TELL01","v":14132,"c":"SanJoseCubing2018"},{"d":"2018-03-10","p":"2016BECE01","v":21724,"c":"SanJoseCubing2018"},{"d":"2018-03-10","p":"2015FELI01","v":27985,"c":"SanJoseCubing2018"},{"d":"2018-04-21","p":"2017RODR25","v":23132,"c":"FIGHTPeru2018"},{"d":"2018-04-21","p":"2015FELI01","v":26974,"c":"FIGHTPeru2018"},{"d":"2018-05-19","p":"2017HUAN07","v":27265,"c":"TorneoActivaClub2018"},{"d":"2018-05-19","p":"2015FELI01","v":26592,"c":"TorneoActivaClub2018"},{"d":"2018-06-29","p":"2017DIBA01","v":26237,"c":"PeruNationals2018"},{"d":"2018-06-29","p":"2017HUAN07","v":25518,"c":"PeruNationals2018"},{"d":"2018-06-29","p":"2013TEMP01","v":26014,"c":"PeruNationals2018"},{"d":"2018-06-29","p":"2018LAUR02","v":28340,"c":"PeruNationals2018"},{"d":"2018-06-29","p":"2015FELI01","v":25262,"c":"PeruNationals2018"},{"d":"2018-07-05","p":"2016SANC08","v":28646,"c":"BoliviaNationals2018"},{"d":"2018-08-04","p":"2016SANC08","v":26232,"c":"CochaCubingI2018"},{"d":"2018-09-29","p":"2017DIBA01","v":23963,"c":"SalesianosOpen2018"},{"d":"2018-09-29","p":"2015SUCL01","v":31458,"c":"SalesianosOpen2018"},{"d":"2018-09-29","p":"2014ZARA01","v":32708,"c":"SalesianosOpen2018"},{"d":"2018-09-29","p":"2016BECE01","v":19432,"c":"SalesianosOpen2018"},{"d":"2018-10-20","p":"2016RODR37","v":31179,"c":"AventuraCubicaVI2018"},{"d":"2018-10-20","p":"2016OBRE01","v":28391,"c":"AventuraCubicaVI2018"},{"d":"2018-10-20","p":"2018LAUR02","v":24135,"c":"AventuraCubicaVI2018"},{"d":"2019-01-12","p":"2017DIBA01","v":23068,"c":"TCGDeluxe2019"},{"d":"2019-01-12","p":"2017AGUI15","v":16809,"c":"TCGDeluxe2019"},{"d":"2019-02-16","p":"2018LAUR02","v":21559,"c":"AventuraCubicaVII2019"},{"d":"2019-02-16","p":"2019JAMB01","v":25347,"c":"AventuraCubicaVII2019"},{"d":"2019-02-16","p":"2017DELG02","v":25776,"c":"AventuraCubicaVII2019"},{"d":"2019-02-16","p":"2016OBRE01","v":26794,"c":"AventuraCubicaVII2019"},{"d":"2019-04-20","p":"2018LAUR02","v":20083,"c":"SpeedcuberPeruOtono2019"},{"d":"2019-04-20","p":"2014RUIZ10","v":21819,"c":"SpeedcuberPeruOtono2019"},{"d":"2019-04-20","p":"2016RODR37","v":25170,"c":"SpeedcuberPeruOtono2019"},{"d":"2019-07-12","p":"2016SANC08","v":24866,"c":"UnifranzSantaCruz2019"},{"d":"2019-08-10","p":"2017AGUI15","v":14678,"c":"PreNacionalesArequipa2019"},{"d":"2019-08-16","p":"2018LAUR02","v":19864,"c":"PeruNationals2019"},{"d":"2019-08-16","p":"2016RODR37","v":23232,"c":"PeruNationals2019"},{"d":"2019-08-16","p":"2017CANT03","v":24906,"c":"PeruNationals2019"},{"d":"2019-08-16","p":"2017SORA01","v":27122,"c":"PeruNationals2019"},{"d":"2019-08-16","p":"2018QUIJ01","v":27248,"c":"PeruNationals2019"},{"d":"2019-09-28","p":"2018LAUR02","v":19668,"c":"ComasSpeedsolving2019"},{"d":"2019-09-28","p":"2017SORA01","v":24580,"c":"ComasSpeedsolving2019"},{"d":"2019-09-28","p":"2018QUIJ01","v":24681,"c":"ComasSpeedsolving2019"},{"d":"2019-09-28","p":"2013TEMP01","v":24819,"c":"ComasSpeedsolving2019"},{"d":"2019-09-28","p":"2017DELG02","v":25095,"c":"ComasSpeedsolving2019"},{"d":"2019-09-28","p":"2017REYE27","v":27455,"c":"ComasSpeedsolving2019"},{"d":"2019-12-06","p":"2016SANC08","v":24223,"c":"BoliviaNationals2019"},{"d":"2019-12-14","p":"2015SUCL01","v":23557,"c":"TCGSpring2019"},{"d":"2019-12-21","p":"2016SANC08","v":23427,"c":"UnifranzElAlto2019"},{"d":"2020-02-29","p":"2018LAUR02","v":18680,"c":"ARomperTuPBLima2020"},{"d":"2020-02-29","p":"2016MILL07","v":20613,"c":"ARomperTuPBLima2020"},{"d":"2020-02-29","p":"2019JAMB01","v":21479,"c":"ARomperTuPBLima2020"},{"d":"2020-02-29","p":"2017DELG02","v":23197,"c":"ARomperTuPBLima2020"},{"d":"2020-02-29","p":"2016OBRE01","v":26784,"c":"ARomperTuPBLima2020"},{"d":"2020-02-29","p":"2017SALA07","v":27244,"c":"ARomperTuPBLima2020"},{"d":"2022-03-12","p":"2018LAUR02","v":18026,"c":"LimaCuberano2022"},{"d":"2022-03-12","p":"2017HUAN07","v":18275,"c":"LimaCuberano2022"},{"d":"2022-03-12","p":"2016MILL07","v":20249,"c":"LimaCuberano2022"},{"d":"2022-03-12","p":"2017SALA07","v":21751,"c":"LimaCuberano2022"},{"d":"2022-03-12","p":"2018QUIJ01","v":22466,"c":"LimaCuberano2022"},{"d":"2022-03-12","p":"2017REYE27","v":23820,"c":"LimaCuberano2022"},{"d":"2022-03-12","p":"2018OCHO03","v":24667,"c":"LimaCuberano2022"},{"d":"2022-03-12","p":"2016OBRE01","v":24725,"c":"LimaCuberano2022"},{"d":"2022-04-30","p":"2018LAUR02","v":17149,"c":"TCGNuevaGeneracion2022"},{"d":"2022-04-30","p":"2017HUAN07","v":17408,"c":"TCGNuevaGeneracion2022"},{"d":"2022-04-30","p":"2016MILL07","v":18075,"c":"TCGNuevaGeneracion2022"},{"d":"2022-04-30","p":"2014RUIZ10","v":18555,"c":"TCGNuevaGeneracion2022"},{"d":"2022-04-30","p":"2017DELG02","v":22316,"c":"TCGNuevaGeneracion2022"},{"d":"2022-04-30","p":"2017REYE27","v":22492,"c":"TCGNuevaGeneracion2022"},{"d":"2022-04-30","p":"2019ALLC01","v":23844,"c":"TCGNuevaGeneracion2022"},{"d":"2022-04-30","p":"2016OBRE01","v":24379,"c":"TCGNuevaGeneracion2022"},{"d":"2022-07-02","p":"2017HUAN07","v":15225,"c":"SchoolWinterLima2022"},{"d":"2022-07-02","p":"2018LAUR02","v":16998,"c":"SchoolWinterLima2022"},{"d":"2022-07-02","p":"2017DELG02","v":22082,"c":"SchoolWinterLima2022"},{"d":"2022-07-02","p":"2019ALLC01","v":23502,"c":"SchoolWinterLima2022"},{"d":"2022-07-02","p":"2016OBRE01","v":24186,"c":"SchoolWinterLima2022"},{"d":"2022-08-06","p":"2016MILL07","v":17926,"c":"RealCube2022"},{"d":"2022-08-06","p":"2017REYE27","v":21468,"c":"RealCube2022"},{"d":"2022-08-06","p":"2017SORA01","v":22903,"c":"RealCube2022"},{"d":"2022-08-06","p":"2019ALLC01","v":23203,"c":"RealCube2022"},{"d":"2022-08-06","p":"2016OBRE01","v":24057,"c":"RealCube2022"},{"d":"2022-08-19","p":"2017QUIS11","v":19845,"c":"PeruNationals2022"},{"d":"2022-08-19","p":"2019TORI04","v":20212,"c":"PeruNationals2022"},{"d":"2022-08-19","p":"2018OCHO03","v":22915,"c":"PeruNationals2022"},{"d":"2022-12-03","p":"2018OCHO03","v":19253,"c":"TCGPowerUp2022"},{"d":"2022-12-03","p":"2017REYE27","v":21184,"c":"TCGPowerUp2022"},{"d":"2022-12-03","p":"2017SORA01","v":22420,"c":"TCGPowerUp2022"},{"d":"2022-12-10","p":"2015VASQ06","v":21432,"c":"UtahSnowballBash2022"},{"d":"2023-02-04","p":"2018LAUR02","v":16000,"c":"LimaSummer2023"},{"d":"2023-02-04","p":"2014RUIZ10","v":17429,"c":"LimaSummer2023"},{"d":"2023-02-04","p":"2016OBRE01","v":22423,"c":"LimaSummer2023"},{"d":"2023-02-04","p":"2017SORA01","v":22417,"c":"LimaSummer2023"},{"d":"2023-02-04","p":"2020CABE02","v":21743,"c":"LimaSummer2023"},{"d":"2023-04-15","p":"2017REYE27","v":20459,"c":"UNSASpeedcubingOtono2023"},{"d":"2023-05-20","p":"2018LAUR02","v":15794,"c":"CubeForceLima2023"},{"d":"2023-05-20","p":"2017SALA07","v":19805,"c":"CubeForceLima2023"},{"d":"2023-05-20","p":"2016MILL07","v":17063,"c":"CubeForceLima2023"},{"d":"2023-05-20","p":"2019ALLC01","v":19140,"c":"CubeForceLima2023"},{"d":"2023-05-20","p":"2017HUAN07","v":15122,"c":"CubeForceLima2023"},{"d":"2023-05-20","p":"2020CABE02","v":20178,"c":"CubeForceLima2023"},{"d":"2023-05-20","p":"2017DELG02","v":21883,"c":"CubeForceLima2023"},{"d":"2023-07-22","p":"2018LAUR02","v":15367,"c":"LimaCubinvierno2023"},{"d":"2023-07-22","p":"2017DELG02","v":21804,"c":"LimaCubinvierno2023"},{"d":"2023-07-22","p":"2016OBRE01","v":21891,"c":"LimaCubinvierno2023"},{"d":"2023-08-04","p":"2017SALA07","v":19082,"c":"PeruNationals2023"},{"d":"2023-08-04","p":"2017REYE27","v":19964,"c":"PeruNationals2023"},{"d":"2023-08-04","p":"2017DELG02","v":21704,"c":"PeruNationals2023"},{"d":"2023-08-04","p":"2015SUCL01","v":22871,"c":"PeruNationals2023"},{"d":"2023-08-12","p":"2020CABE02","v":20012,"c":"SanMarcosOpen2023"},{"d":"2023-08-12","p":"2016RODR37","v":20613,"c":"SanMarcosOpen2023"},{"d":"2023-08-12","p":"2017SORA01","v":21058,"c":"SanMarcosOpen2023"},{"d":"2023-08-19","p":"2017HUAN07","v":15091,"c":"LaTiendaCuberaFest2023"},{"d":"2023-08-19","p":"2014RUIZ10","v":16961,"c":"LaTiendaCuberaFest2023"},{"d":"2023-08-19","p":"2018OCHO03","v":19057,"c":"LaTiendaCuberaFest2023"},{"d":"2023-08-19","p":"2017DELG02","v":20671,"c":"LaTiendaCuberaFest2023"},{"d":"2023-09-03","p":"2017HUAN07","v":15046,"c":"ChosicaCubingCup2023"},{"d":"2023-09-03","p":"2018OCHO03","v":18352,"c":"ChosicaCubingCup2023"},{"d":"2023-09-03","p":"2017DELG02","v":20040,"c":"ChosicaCubingCup2023"},{"d":"2023-09-03","p":"2016RODR37","v":20515,"c":"ChosicaCubingCup2023"},{"d":"2023-09-16","p":"2017HUAN07","v":15009,"c":"PlazaCenterCubeLimaI2023"},{"d":"2023-09-16","p":"2016MILL07","v":16770,"c":"PlazaCenterCubeLimaI2023"},{"d":"2023-09-16","p":"2015FELI01","v":24627,"c":"PlazaCenterCubeLimaI2023"},{"d":"2023-09-30","p":"2015ACHA01","v":24026,"c":"PlazaCenterCubeLimaII2023"},{"d":"2023-11-04","p":"2017REYE27","v":19955,"c":"RealGeekcuberPucallpa2023"},{"d":"2023-12-16","p":"2016MILL07","v":16504,"c":"SpeedcuberPeruIILima2023"},{"d":"2023-12-16","p":"2018OCHO03","v":18113,"c":"SpeedcuberPeruIILima2023"},{"d":"2023-12-16","p":"2017REYE27","v":18887,"c":"SpeedcuberPeruIILima2023"},{"d":"2024-01-14","p":"2015TELL01","v":13837,"c":"ChosicasBigShow2024"},{"d":"2024-01-14","p":"2018LAUR02","v":14656,"c":"ChosicasBigShow2024"},{"d":"2024-01-14","p":"2017HUAN07","v":14932,"c":"ChosicasBigShow2024"},{"d":"2024-01-14","p":"2018OCHO03","v":17334,"c":"ChosicasBigShow2024"},{"d":"2024-01-14","p":"2017SALA07","v":18169,"c":"ChosicasBigShow2024"},{"d":"2024-01-14","p":"2017DELG02","v":19258,"c":"ChosicasBigShow2024"},{"d":"2024-01-14","p":"2018QUIJ01","v":20545,"c":"ChosicasBigShow2024"},{"d":"2024-02-10","p":"2017DELG02","v":19089,"c":"PlazaCenterCubeLimalll2024"},{"d":"2024-05-04","p":"2018QUIJ01","v":19472,"c":"ChambeaenTuPBLima2024"},{"d":"2024-06-01","p":"2016SANC08","v":23142,"c":"CatoCubingCochabamba2024"},{"d":"2024-10-08","p":"2018OCHO03","v":16937,"c":"CaballerodelosMaresLima2024"},{"d":"2024-10-08","p":"2018QUIJ01","v":19417,"c":"CaballerodelosMaresLima2024"},{"d":"2024-10-19","p":"2018QUIJ01","v":18926,"c":"OsoCubingFestILima2024"},{"d":"2024-11-02","p":"2016OBRE01","v":21823,"c":"PUCPCubingFestivallll2024"},{"d":"2024-11-22","p":"2016MILL07","v":16025,"c":"PeruNationals2024"},{"d":"2024-11-22","p":"2018OCHO03","v":15846,"c":"PeruNationals2024"},{"d":"2024-11-22","p":"2017DELG02","v":19003,"c":"PeruNationals2024"},{"d":"2024-11-22","p":"2017REYE27","v":18642,"c":"PeruNationals2024"},{"d":"2024-11-22","p":"2023ROJA17","v":23451,"c":"PeruNationals2024"},{"d":"2024-12-06","p":"2016SANC08","v":22617,"c":"BoliviaNationals2024"},{"d":"2025-01-25","p":"2017DELG02","v":17924,"c":"LosReyesdelCuboChiclayoIII2025"},{"d":"2025-01-25","p":"2022NUNU03","v":21560,"c":"LosReyesdelCuboChiclayoIII2025"},{"d":"2025-01-25","p":"2017REYE27","v":18440,"c":"LosReyesdelCuboChiclayoIII2025"},{"d":"2025-02-22","p":"2018LAUR02","v":14387,"c":"PUCPCubingFestivalIV2025"},{"d":"2025-02-22","p":"2017REYE27","v":18392,"c":"PUCPCubingFestivalIV2025"},{"d":"2025-02-22","p":"2022NUNU03","v":20820,"c":"PUCPCubingFestivalIV2025"},{"d":"2025-04-05","p":"2018OCHO03","v":15766,"c":"PlazaCenterCubeLimaVI2025"},{"d":"2025-05-31","p":"2016MILL07","v":16005,"c":"OsoCubingFestIILima2025"},{"d":"2025-07-19","p":"2017RODR25","v":18893,"c":"PUCPCubingFestivalV2025"},{"d":"2025-07-19","p":"2022NUNU03","v":20262,"c":"PUCPCubingFestivalV2025"},{"d":"2025-07-19","p":"2018OCHO03","v":15647,"c":"PUCPCubingFestivalV2025"},{"d":"2025-08-24","p":"2023CHUG02","v":21721,"c":"PUCPCubingFestivalVI2025"},{"d":"2025-08-24","p":"2017REYE27","v":18137,"c":"PUCPCubingFestivalVI2025"},{"d":"2025-08-29","p":"2018LAUR02","v":14257,"c":"PeruNationals2025"},{"d":"2025-08-29","p":"2016MILL07","v":15472,"c":"PeruNationals2025"},{"d":"2025-08-29","p":"2023ROJA17","v":19420,"c":"PeruNationals2025"},{"d":"2025-08-29","p":"2017HUAN07","v":14357,"c":"PeruNationals2025"},{"d":"2025-08-29","p":"2015SUCL01","v":20309,"c":"PeruNationals2025"},{"d":"2025-08-29","p":"2018OCHO03","v":15487,"c":"PeruNationals2025"},{"d":"2025-10-10","p":"2016SANC08","v":21744,"c":"SantaCruzNxN2025"},{"d":"2025-10-19","p":"2023CHUG02","v":21063,"c":"PUCPCubingFestivalVII2025"},{"d":"2025-10-19","p":"2016OBRE01","v":20758,"c":"PUCPCubingFestivalVII2025"},{"d":"2025-12-07","p":"2023CHUG02","v":19456,"c":"PUCPCubingFestivalVIII2025"},{"d":"2025-12-07","p":"2022NUNU03","v":18105,"c":"PUCPCubingFestivalVIII2025"},{"d":"2025-12-07","p":"2018OCHO03","v":14605,"c":"PUCPCubingFestivalVIII2025"},{"d":"2025-12-13","p":"2024PALO06","v":18466,"c":"ArmandoSuenosBlenkir2025"},{"d":"2025-12-13","p":"2017HUAN07","v":14282,"c":"ArmandoSuenosBlenkir2025"},{"d":"2025-12-13","p":"2016MILL07","v":14818,"c":"ArmandoSuenosBlenkir2025"},{"d":"2025-12-13","p":"2018QUIJ01","v":18485,"c":"ArmandoSuenosBlenkir2025"},{"d":"2025-12-20","p":"2016SANC08","v":21006,"c":"MYHMBoliviaNationals2025"},{"d":"2026-01-23","p":"2017HUAN07","v":13890,"c":"SteelsCubesLima2026"},{"d":"2026-01-23","p":"2016OBRE01","v":20023,"c":"SteelsCubesLima2026"},{"d":"2026-01-23","p":"2016RODR37","v":19302,"c":"SteelsCubesLima2026"},{"d":"2026-01-30","p":"2016SANC08","v":20658,"c":"SanCristobalOpenSucre2026"},{"d":"2026-02-21","p":"2015VASQ06","v":20411,"c":"CubingwithDinosaursLehi2026"},{"d":"2026-02-28","p":"2018QUIJ01","v":18224,"c":"SummeroftheCubeHuancayo2026"},{"d":"2026-03-07","p":"2017HUAN07","v":13426,"c":"PUCPCubingFestivalIX2026"},{"d":"2026-03-07","p":"2023CHUG02","v":19288,"c":"PUCPCubingFestivalIX2026"},{"d":"2026-03-21","p":"2018OCHO03","v":14513,"c":"PUCPCubingFestivalX2026"},{"d":"2026-03-21","p":"2023CHUG02","v":18803,"c":"PUCPCubingFestivalX2026"}],"average_r":[{"d":"2013-01-05","p":"2011QUEZ01","v":49213,"c":"CampeonatoSudamericano2013"},{"d":"2013-04-05","p":"2011LUJA01","v":36668,"c":"NacionalPerubik2013"},{"d":"2013-04-05","p":"2011QUEZ01","v":44688,"c":"NacionalPerubik2013"},{"d":"2013-04-05","p":"2013VALD02","v":44724,"c":"NacionalPerubik2013"},{"d":"2013-07-20","p":"2013VALD02","v":35463,"c":"TrujilloOpen2013"},{"d":"2013-07-20","p":"2012ROBL01","v":36992,"c":"TrujilloOpen2013"},{"d":"2013-07-20","p":"2011LUJA01","v":42794,"c":"TrujilloOpen2013"},{"d":"2013-10-04","p":"2011ARAN01","v":40605,"c":"MarianoMelgar2013"},{"d":"2013-10-04","p":"2011CUBA02","v":45931,"c":"MarianoMelgar2013"},{"d":"2013-10-26","p":"2013CAST06","v":30931,"c":"PalacioDelCubo2013"},{"d":"2013-10-26","p":"2012ROBL01","v":31320,"c":"PalacioDelCubo2013"},{"d":"2013-10-26","p":"2011QUEZ01","v":41681,"c":"PalacioDelCubo2013"},{"d":"2013-10-26","p":"2011CUBA02","v":50072,"c":"PalacioDelCubo2013"},{"d":"2013-10-26","p":"2011CORA01","v":51046,"c":"PalacioDelCubo2013"},{"d":"2014-02-07","p":"2013VALD02","v":26525,"c":"CulturalOpen2014"},{"d":"2014-02-07","p":"2011CUBA02","v":48198,"c":"CulturalOpen2014"},{"d":"2014-03-08","p":"2013VALD02","v":25383,"c":"BackToThePalace2014"},{"d":"2014-03-08","p":"2013CAST06","v":28938,"c":"BackToThePalace2014"},{"d":"2014-03-08","p":"2012ROBL01","v":32212,"c":"BackToThePalace2014"},{"d":"2014-03-08","p":"2011QUEZ01","v":44315,"c":"BackToThePalace2014"},{"d":"2014-06-20","p":"2011CUBA02","v":40291,"c":"UniRubik2014"},{"d":"2014-07-12","p":"2013VALD02","v":25250,"c":"MarianoMelgar2014"},{"d":"2014-07-12","p":"2011CUBA02","v":41739,"c":"MarianoMelgar2014"},{"d":"2014-09-06","p":"2011QUEZ01","v":36154,"c":"TCGLima2014"},{"d":"2014-10-24","p":"2011CUBA02","v":36868,"c":"IIOpenArguedas2014"},{"d":"2014-10-24","p":"2013VERA03","v":41650,"c":"IIOpenArguedas2014"},{"d":"2015-01-31","p":"2015TELL01","v":23614,"c":"NewAvgeOpen2015"},{"d":"2015-01-31","p":"2013HUAN30","v":34854,"c":"NewAvgeOpen2015"},{"d":"2015-06-13","p":"2015TELL01","v":21890,"c":"HunterOpen2015"},{"d":"2015-06-13","p":"2011CUBA02","v":26207,"c":"HunterOpen2015"},{"d":"2015-07-08","p":"2015TELL01","v":22262,"c":"TCGAndFriendsAQP2015"},{"d":"2015-07-11","p":"2015TELL01","v":21775,"c":"TCGAndFriends2015"},{"d":"2015-07-11","p":"2014GUTI04","v":34289,"c":"TCGAndFriends2015"},{"d":"2015-07-17","p":"2015TELL01","v":20892,"c":"WC2015"},{"d":"2015-07-17","p":"2015TELL01","v":21326,"c":"WC2015"},{"d":"2015-09-26","p":"2011CUBA02","v":26918,"c":"CochabambaOpen2015"},{"d":"2016-01-23","p":"2015TELL01","v":19297,"c":"TorneoAventuraCubica2016"},{"d":"2016-02-12","p":"2011CUBA02","v":22536,"c":"UchiMontevideo2016"},{"d":"2016-02-12","p":"2011CUBA02","v":23955,"c":"UchiMontevideo2016"},{"d":"2016-03-20","p":"2015TELL01","v":18288,"c":"CrazyCubesSummer2016"},{"d":"2016-06-04","p":"2015TELL01","v":22294,"c":"TorneoCosmocentro2016"},{"d":"2016-07-01","p":"2015TELL01","v":19110,"c":"BoliviaNationals2016"},{"d":"2016-07-01","p":"2015TELL01","v":19592,"c":"BoliviaNationals2016"},{"d":"2016-07-01","p":"2011CUBA02","v":20693,"c":"BoliviaNationals2016"},{"d":"2016-07-01","p":"2011CUBA02","v":23286,"c":"BoliviaNationals2016"},{"d":"2016-07-16","p":"2015TELL01","v":19352,"c":"NacionalPerubik2016"},{"d":"2016-08-13","p":"2015TELL01","v":20562,"c":"GameProTour2016"},{"d":"2017-02-04","p":"2015TELL01","v":16267,"c":"AventuraCubicaIII2017"},{"d":"2017-06-17","p":"2011CUBA02","v":20209,"c":"LatinAmericaCubingTourCochab2017"},{"d":"2017-06-24","p":"2015TELL01","v":15858,"c":"LatinAmericaCubingTourLima2017"},{"d":"2017-06-24","p":"2011CUBA02","v":20426,"c":"LatinAmericaCubingTourLima2017"},{"d":"2017-07-22","p":"2015TELL01","v":16050,"c":"LTCCubeFest2017"},{"d":"2017-08-26","p":"2015TELL01","v":17659,"c":"CampeonatoNacionalPerubik2017"},{"d":"2017-08-26","p":"2011CUBA02","v":18933,"c":"CampeonatoNacionalPerubik2017"},{"d":"2017-08-26","p":"2013VALD02","v":20417,"c":"CampeonatoNacionalPerubik2017"},{"d":"2017-12-16","p":"2015TELL01","v":14601,"c":"CrazyCubesChristmas2017"},{"d":"2018-01-27","p":"2015TELL01","v":15646,"c":"AventuraCubicaV2018"},{"d":"2018-03-10","p":"2015TELL01","v":14132,"c":"SanJoseCubing2018"},{"d":"2018-04-21","p":"2015TELL01","v":14552,"c":"FIGHTPeru2018"},{"d":"2018-05-19","p":"2015TELL01","v":17188,"c":"TorneoActivaClub2018"},{"d":"2018-06-29","p":"2015TELL01","v":16127,"c":"PeruNationals2018"},{"d":"2018-07-19","p":"2015TELL01","v":14355,"c":"Euro2018"},{"d":"2018-10-20","p":"2015TELL01","v":15549,"c":"AventuraCubicaVI2018"},{"d":"2018-11-03","p":"2015TELL01","v":15363,"c":"IquitosCubing2018"},{"d":"2018-12-15","p":"2015TELL01","v":16319,"c":"SouthAmericanChampionship2018"},{"d":"2019-01-12","p":"2017AGUI15","v":16809,"c":"TCGDeluxe2019"},{"d":"2019-08-10","p":"2017AGUI15","v":14678,"c":"PreNacionalesArequipa2019"},{"d":"2019-08-16","p":"2015TELL01","v":15124,"c":"PeruNationals2019"},{"d":"2019-09-28","p":"2015TELL01","v":15158,"c":"ComasSpeedsolving2019"},{"d":"2019-12-14","p":"2017AGUI15","v":15292,"c":"TCGSpring2019"},{"d":"2022-07-02","p":"2017HUAN07","v":15225,"c":"SchoolWinterLima2022"},{"d":"2023-02-04","p":"2017HUAN07","v":15954,"c":"LimaSummer2023"},{"d":"2023-02-04","p":"2018LAUR02","v":16000,"c":"LimaSummer2023"},{"d":"2023-05-20","p":"2017HUAN07","v":15122,"c":"CubeForceLima2023"},{"d":"2023-05-20","p":"2018LAUR02","v":15794,"c":"CubeForceLima2023"},{"d":"2023-07-22","p":"2017HUAN07","v":15122,"c":"LimaCubinvierno2023"},{"d":"2023-07-22","p":"2018LAUR02","v":15367,"c":"LimaCubinvierno2023"},{"d":"2023-07-22","p":"2015TELL01","v":15427,"c":"LimaCubinvierno2023"},{"d":"2023-08-04","p":"2015TELL01","v":14218,"c":"PeruNationals2023"},{"d":"2023-08-04","p":"2017HUAN07","v":15149,"c":"PeruNationals2023"},{"d":"2023-08-12","p":"2015TELL01","v":14774,"c":"SanMarcosOpen2023"},{"d":"2023-08-19","p":"2015TELL01","v":14457,"c":"LaTiendaCuberaFest2023"},{"d":"2023-08-19","p":"2017HUAN07","v":15091,"c":"LaTiendaCuberaFest2023"},{"d":"2023-09-03","p":"2015TELL01","v":14737,"c":"ChosicaCubingCup2023"},{"d":"2023-09-03","p":"2017HUAN07","v":15046,"c":"ChosicaCubingCup2023"},{"d":"2023-09-16","p":"2017HUAN07","v":15009,"c":"PlazaCenterCubeLimaI2023"},{"d":"2023-09-30","p":"2015TELL01","v":14909,"c":"PlazaCenterCubeLimaII2023"},{"d":"2023-09-30","p":"2017HUAN07","v":15097,"c":"PlazaCenterCubeLimaII2023"},{"d":"2023-11-04","p":"2015TELL01","v":14482,"c":"RealGeekcuberPucallpa2023"},{"d":"2024-01-14","p":"2015TELL01","v":13837,"c":"ChosicasBigShow2024"},{"d":"2024-01-14","p":"2018LAUR02","v":14656,"c":"ChosicasBigShow2024"},{"d":"2024-01-14","p":"2017HUAN07","v":14932,"c":"ChosicasBigShow2024"},{"d":"2024-03-02","p":"2018LAUR02","v":14960,"c":"PlazaCenterCubeLimaIV2024"},{"d":"2024-05-04","p":"2015TELL01","v":14108,"c":"ChambeaenTuPBLima2024"},{"d":"2025-02-22","p":"2018LAUR02","v":14387,"c":"PUCPCubingFestivalIV2025"},{"d":"2025-07-19","p":"2018LAUR02","v":14568,"c":"PUCPCubingFestivalV2025"},{"d":"2025-08-29","p":"2018LAUR02","v":14257,"c":"PeruNationals2025"},{"d":"2025-08-29","p":"2017HUAN07","v":14357,"c":"PeruNationals2025"},{"d":"2025-12-07","p":"2018OCHO03","v":14605,"c":"PUCPCubingFestivalVIII2025"},{"d":"2025-12-13","p":"2017HUAN07","v":14282,"c":"ArmandoSuenosBlenkir2025"},{"d":"2026-01-23","p":"2017HUAN07","v":13890,"c":"SteelsCubesLima2026"},{"d":"2026-02-28","p":"2017HUAN07","v":13890,"c":"SummeroftheCubeHuancayo2026"},{"d":"2026-03-07","p":"2017HUAN07","v":13426,"c":"PUCPCubingFestivalIX2026"},{"d":"2026-03-21","p":"2017HUAN07","v":13735,"c":"PUCPCubingFestivalX2026"},{"d":"2026-06-12","p":"2017HUAN07","v":14336,"c":"SAC2026"}],"persons":{"2010MOND01":{"name":"Pablo Nicolás Oshiro Mondoñedo","country":"Peru","iso2":"PE"},"2011QUEZ01":{"name":"Noel Yzaguirre","country":"Peru","iso2":"PE"},"2011ARAN01":{"name":"Maximiliano Arana","country":"Peru","iso2":"PE"},"2011LUJA01":{"name":"Juan Javier Quispe Lujan","country":"Peru","iso2":"PE"},"2013VALD02":{"name":"Christian Saenz Valdivia","country":"Peru","iso2":"PE"},"2012ROBL01":{"name":"Erik Paico Robles","country":"Peru","iso2":"PE"},"2011CUBA02":{"name":"Ernesto Gutiérrez Cuba","country":"Peru","iso2":"PE"},"2013CAST06":{"name":"Angelo Vega Castillo","country":"Peru","iso2":"PE"},"2011CORA01":{"name":"Daniel Alber Ninaquispe Corales","country":"Peru","iso2":"PE"},"2013VERA03":{"name":"Andres Armando Montalvo Vera","country":"Peru","iso2":"PE"},"2013HUAN03":{"name":"Hector Huanqque","country":"Peru","iso2":"PE"},"2013TEMP01":{"name":"Jhon Alexander Taboada Temple","country":"Peru","iso2":"PE"},"2013BERD02":{"name":"Dewin Berdejo","country":"Peru","iso2":"PE"},"2013HUAN30":{"name":"Juan Pablo Huanqui","country":"Peru","iso2":"PE"},"2015TELL01":{"name":"Pedro Alejandro Condo Tellez","country":"Peru","iso2":"PE"},"2014GUTI04":{"name":"Jesus Crisostomo Gutierrez","country":"Peru","iso2":"PE"},"2015ELIA03":{"name":"Alonso Sanchez Elias","country":"Peru","iso2":"PE"},"2014CORD04":{"name":"Freddy Fernández Córdova","country":"Peru","iso2":"PE"},"2013ANAM01":{"name":"Angel Anampa","country":"Peru","iso2":"PE"},"2014ZARA01":{"name":"Rodrigo Zarate","country":"Peru","iso2":"PE"},"2014RUIZ10":{"name":"Kevin Arturo Huamán Ruiz","country":"Peru","iso2":"PE"},"2015SUCL01":{"name":"Pedro Luis Mamani Suclla","country":"Peru","iso2":"PE"},"2015VASQ06":{"name":"Jarry Tapia Vasquez","country":"Peru","iso2":"PE"},"2016SANC08":{"name":"Joseph Daniel Blas Sanchez","country":"Peru","iso2":"PE"},"2015FELI01":{"name":"Walter Felix","country":"Peru","iso2":"PE"},"2016OBRE01":{"name":"Piero Alessandro Laguna Obregon","country":"Peru","iso2":"PE"},"2016BECE01":{"name":"Smeling Becerra","country":"Peru","iso2":"PE"},"2017RODR25":{"name":"Abel Jesús Rodriguez Alvarado","country":"Peru","iso2":"PE"},"2016ELIA02":{"name":"César Chalco Elías","country":"Peru","iso2":"PE"},"2015ACHA01":{"name":"Leon Achata","country":"Peru","iso2":"PE"},"2017DIBA01":{"name":"Daniel Esteban Rivera Diban","country":"Peru","iso2":"PE"},"2016VARG04":{"name":"Kevin Estefano Coayla Vargas","country":"Peru","iso2":"PE"},"2017FLOR01":{"name":"Lucciano Florez","country":"Peru","iso2":"PE"},"2017AGUI15":{"name":"Marco Antonio Ponce de León Aguilar","country":"Peru","iso2":"PE"},"2017HUAN07":{"name":"Marcelo Nuñez","country":"Peru","iso2":"PE"},"2017DELG02":{"name":"Kevin Antony Tello Delgado","country":"Peru","iso2":"PE"},"2016RODR37":{"name":"Angel Jesus Panebra Rodriguez","country":"Peru","iso2":"PE"},"2018LAUR02":{"name":"Ricardo Sanchez Laurencio","country":"Peru","iso2":"PE"},"2016NUNE15":{"name":"Valentino Nuñez","country":"Peru","iso2":"PE"},"2017SALA07":{"name":"Ronald Fernando Remuzgo Salazar","country":"Peru","iso2":"PE"},"2019JAMB01":{"name":"Keener Zamudio Jambo","country":"Peru","iso2":"PE"},"2018QUIJ01":{"name":"Michel Andre Gonzaga Quijano","country":"Peru","iso2":"PE"},"2017REYE27":{"name":"Jose Caldas","country":"Peru","iso2":"PE"},"2019ALLC01":{"name":"Giordano Limber Aguilar Allcca","country":"Peru","iso2":"PE"},"2019TORI04":{"name":"José Luis Tarapacá Toribio","country":"Peru","iso2":"PE"},"2016MILL07":{"name":"Pedro Giuseppe Garcia Milla","country":"Peru","iso2":"PE"},"2018OCHO03":{"name":"Benjamín Ochoa","country":"Peru","iso2":"PE"},"2017QUIS11":{"name":"Dan Axel Gonzales Quispe","country":"Peru","iso2":"PE"},"2020CABE02":{"name":"Elias Alonso Usaqui Cabezas","country":"Peru","iso2":"PE"},"2023ROJA17":{"name":"Marlon Rojas","country":"Peru","iso2":"PE"},"2022NUNU03":{"name":"Miguel Ángel Sánchez Nunura","country":"Peru","iso2":"PE"},"2023CHUG02":{"name":"Leonardo Aldair Trujillo Chugden","country":"Peru","iso2":"PE"},"2024PALO06":{"name":"Alberto Mitsuo Cruz Palomino","country":"Peru","iso2":"PE"},"2017CANT03":{"name":"Carlos Quispe Cantorin","country":"Peru","iso2":"PE"},"2017SORA01":{"name":"Abraham Arcila Soraluz","country":"Peru","iso2":"PE"}},"comps":{"SpanishChampionship2011":{"name":"Spanish Championship 2011"},"BarcelonaWinterOpen2012":{"name":"Barcelona Winter Open 2012"},"CampeonatoSudamericano2013":{"name":"Sudamericano 2013"},"UAMOpen2013":{"name":"UAM Open 2013"},"ArequipaSummer2013":{"name":"Arequipa Summer 2013"},"NacionalPerubik2013":{"name":"Nacional Perubik 2013"},"TrujilloOpen2013":{"name":"Trujillo 2013"},"MarianoMelgar2013":{"name":"Mariano Melgar 2013"},"PalacioDelCubo2013":{"name":"Palacio del Cubo 2013"},"CulturalOpen2014":{"name":"Cultural Open 2014"},"BackToThePalace2014":{"name":"Back to the Palace 2014"},"UniRubik2014":{"name":"UNI-Rubik 2014"},"MarianoMelgar2014":{"name":"Mariano Melgar 2014"},"TCGLima2014":{"name":"TCG Lima 2014"},"IIOpenArguedas2014":{"name":"II Open Arguedas 2014"},"GameProTour2014":{"name":"Game Pro Tour 2014"},"NewAvgeOpen2015":{"name":"New Avge Open 2015"},"HunterOpen2015":{"name":"Hunter Open 2015"},"TCGAndFriendsAQP2015":{"name":"TCG & Friends AQP 2015"},"TCGAndFriends2015":{"name":"TCG & Friends 2015"},"WC2015":{"name":"World Championship 2015"},"TorneoAventuraCubica2016":{"name":"Aventura Cubica 2016"},"UchiMontevideo2016":{"name":"Uchi Montevideo 2016"},"CrazyCubesSummer2016":{"name":"Crazy Cubes Summer 2016"},"BoliviaNationals2016":{"name":"Bolivia Nationals 2016"},"NacionalPerubik2016":{"name":"Nacional Perubik 2016"},"GameProTour2016":{"name":"Game Pro Tour 2016"},"YoRubik2016":{"name":"Yo Rubik 2016"},"TaiwanChampionship2016":{"name":"Taiwan Championship 2016"},"SantaCruzRubiksChallengue2017":{"name":"Santa Cruz 2017"},"AventuraCubicaIII2017":{"name":"Aventura Cúbica III 2017"},"CopaRubikSimonIPatino2017":{"name":"Copa Rubik Simon I. Patiño 2017"},"LatinAmericaCubingTourCochab2017":{"name":"LatAm Tour - Cochabamba 2017"},"LatinAmericaCubingTourLima2017":{"name":"LatAm Tour - Lima 2017"},"LTCCubeFest2017":{"name":"LTC Cube Fest 2017"},"CampeonatoNacionalPerubik2017":{"name":"Campeonato Nacional Perubik 2017"},"YoRubik20SC2017":{"name":"Yo Rubik 2.0 S-C 2017"},"CrazyCubesChristmas2017":{"name":"Crazy Cubes Christmas 2017"},"EkekoRubik2018":{"name":"Ekeko Rubik 2018"},"UnivalleBigCubes2018":{"name":"Univalle Big Cubes 2018"},"AventuraCubicaV2018":{"name":"Aventura Cúbica V 2018"},"SanJoseCubing2018":{"name":"San Jose Cubing 2018"},"FIGHTPeru2018":{"name":"FIGHT Peru 2018"},"TorneoActivaClub2018":{"name":"Torneo Activa Club 2018"},"PeruNationals2018":{"name":"Peru Nationals 2018"},"BoliviaNationals2018":{"name":"Bolivia Nationals 2018"},"CochaCubingI2018":{"name":"Cocha Cubing I 2018"},"SalesianosOpen2018":{"name":"Salesianos Open 2018"},"AventuraCubicaVI2018":{"name":"Aventura Cúbica VI 2018"},"IquitosCubing2018":{"name":"Iquitos Cubing 2018"},"TCGDeluxe2019":{"name":"TCG Deluxe 2019"},"SanRafaelSummer2019":{"name":"San Rafael Summer 2019"},"AventuraCubicaVII2019":{"name":"Aventura Cúbica VII 2019"},"SpeedcuberPeruOtono2019":{"name":"Speedcuber Perú Otoño 2019"},"UnifranzSantaCruz2019":{"name":"Unifranz Santa Cruz 2019"},"PreNacionalesArequipa2019":{"name":"Pre-Nacionales Arequipa 2019"},"PeruNationals2019":{"name":"Peru Nationals 2019"},"ComasSpeedsolving2019":{"name":"Comas Speedsolving 2019"},"UnifranzSpringCubingFest2019":{"name":"Unifranz Spring Cubing Fest 2019"},"BoliviaNationals2019":{"name":"Bolivia Nationals 2019"},"TCGSpring2019":{"name":"TCG Spring 2019"},"UnifranzElAlto2019":{"name":"Unifranz El Alto 2019"},"ARomperTuPBLima2020":{"name":"A Romper Tu PB Lima 2020"},"LimaCuberano2022":{"name":"Lima Cuberano 2022"},"TCGNuevaGeneracion2022":{"name":"TCG Nueva Generación 2022"},"SchoolWinterLima2022":{"name":"School Winter Lima 2022"},"RealCube2022":{"name":"Real Cube 2022"},"PeruNationals2022":{"name":"Peru Nationals 2022"},"TCGPowerUp2022":{"name":"TCG Power Up 2022"},"UtahSnowballBash2022":{"name":"Utah Snowball Bash 2022"},"IdahoFreezeDried2023":{"name":"Idaho Freeze Dried 2023"},"LimaSummer2023":{"name":"Lima Summer 2023"},"UNSASpeedcubingOtono2023":{"name":"UNSA Speedcubing Otoño 2023"},"CubeForceLima2023":{"name":"Cube Force Lima 2023"},"LimaCubinvierno2023":{"name":"Lima Cubinvierno 2023"},"PeruNationals2023":{"name":"Peru Nationals 2023"},"SanMarcosOpen2023":{"name":"San Marcos Open 2023"},"LaTiendaCuberaFest2023":{"name":"La Tienda Cubera Fest 2023"},"ChosicaCubingCup2023":{"name":"Chosica Cubing Cup 2023"},"PlazaCenterCubeLimaI2023":{"name":"Plaza Center Cube Lima I 2023"},"PlazaCenterCubeLimaII2023":{"name":"Plaza Center Cube Lima II 2023"},"SpeedcuberPeruIILima2023":{"name":"Speedcuber Peru II Lima 2023"},"ChosicasBigShow2024":{"name":"Chosica's Big Show 2024"},"PlazaCenterCubeLimalll2024":{"name":"Plaza Center Cube Lima lll 2024"},"ChambeaenTuPBLima2024":{"name":"Chambea en Tu PB Lima 2024"},"OpenPUCPCubingCommunity2024":{"name":"Open PUCP Cubing Community 2024"},"ValdAranOpen2024":{"name":"Val d'Aran Open 2024"},"CaballerodelosMaresLima2024":{"name":"Caballero de los Mares Lima 2024"},"PeruNationals2024":{"name":"Peru Nationals 2024"},"LosReyesdelCuboChiclayoIII2025":{"name":"Los Reyes del Cubo III 2025"},"PUCPCubingFestivalIV2025":{"name":"PUCP Cubing Festival IV 2025"},"ValldeNuria2025":{"name":"Vall de Núria 2025"},"PUCPCubingFestivalV2025":{"name":"PUCP Cubing Festival V 2025"},"PUCPCubingFestivalVI2025":{"name":"PUCP Cubing Festival VI 2025"},"PeruNationals2025":{"name":"Peru Nationals 2025"},"SantaCruzNxN2025":{"name":"Santa Cruz NxN 2025"},"PUCPCubingFestivalVII2025":{"name":"PUCP Cubing Festival VII 2025"},"UtahChampionship2025":{"name":"Utah Championship 2025"},"PUCPCubingFestivalVIII2025":{"name":"PUCP Cubing Festival VIII 2025"},"ArmandoSuenosBlenkir2025":{"name":"Armando Sueños Blenkir 2025"},"MYHMBoliviaNationals2025":{"name":"MYHM Bolivia Nationals 2025"},"SteelsCubesLima2026":{"name":"Steel's Cubes Lima 2026"},"CubingwithDinosaursLehi2026":{"name":"Cubing with Dinosaurs Lehi 2026"},"SummeroftheCubeHuancayo2026":{"name":"Summer of the Cube Huancayo 2026"},"PUCPCubingFestivalIX2026":{"name":"PUCP Cubing Festival IX 2026"},"PUCPCubingFestivalX2026":{"name":"PUCP Cubing Festival X 2026"},"UnicenOpenSCZ2026":{"name":"Unicen Open SCZ 2026"},"CochabambaOpen2015":{"name":"Cochabamba Open 2015"},"TorneoCosmocentro2016":{"name":"Cosmocentro 2016"},"Euro2018":{"name":"WCA Euro 2018"},"SouthAmericanChampionship2018":{"name":"South American Championship 2018"},"RealGeekcuberPucallpa2023":{"name":"Real Geekcuber Pucallpa 2023"},"PlazaCenterCubeLimaIV2024":{"name":"Plaza Center Cube Lima IV 2024"},"SAC2026":{"name":"SAC 2026"},"CatoCubingCochabamba2024":{"name":"Cato Cubing Cochabamba 2024"},"OsoCubingFestILima2024":{"name":"Oso Cubing Fest I Lima 2024"},"PUCPCubingFestivallll2024":{"name":"PUCP Cubing Festival lll 2024"},"BoliviaNationals2024":{"name":"Bolivia Nationals 2024"},"PlazaCenterCubeLimaVI2025":{"name":"Plaza Center Cube Lima VI 2025"},"OsoCubingFestIILima2025":{"name":"Oso Cubing Fest II Lima 2025"},"SanCristobalOpenSucre2026":{"name":"San Cristobal Open Sucre 2026"}}}